{"v":"5.12.1","fr":29.9700012207031,"ip":0,"op":150.000006109625,"w":500,"h":500,"nm":"Agreement","ddd":0,"assets":[],"layers":[{"ddd":0,"ind":2,"ty":4,"nm":"Layer 20 Outlines - Group 1","parent":3,"sr":1,"ks":{"o":{"a":0,"k":100,"ix":11},"r":{"a":0,"k":0,"ix":10},"p":{"a":0,"k":[252,131.816,0],"ix":2,"l":2},"a":{"a":0,"k":[32.65,8.613,0],"ix":1,"l":2},"s":{"a":1,"k":[{"i":{"x":[0.63,0.63,0.63],"y":[1,1,1]},"o":{"x":[0.37,0.37,0.37],"y":[0,0,0]},"t":38,"s":[0,0,100]},{"i":{"x":[0.63,0.63,0.63],"y":[1,1,1]},"o":{"x":[0.37,0.37,0.37],"y":[0,0,0]},"t":48,"s":[550,550,100]},{"i":{"x":[0.63,0.63,0.63],"y":[1,1,1]},"o":{"x":[0.37,0.37,0.37],"y":[0,0,0]},"t":58,"s":[400,400,100]},{"i":{"x":[0.63,0.63,0.63],"y":[1,1,1]},"o":{"x":[0.37,0.37,0.37],"y":[0,0,0]},"t":68,"s":[550,550,100]},{"i":{"x":[0.833,0.833,0.833],"y":[1,1,1]},"o":{"x":[0.167,0.167,0.167],"y":[0,0,0]},"t":78,"s":[0,0,100]},{"i":{"x":[0.63,0.63,0.63],"y":[1,1,1]},"o":{"x":[0.37,0.37,0.37],"y":[0,0,0]},"t":113,"s":[0,0,100]},{"i":{"x":[0.63,0.63,0.63],"y":[1,1,1]},"o":{"x":[0.37,0.37,0.37],"y":[0,0,0]},"t":123,"s":[550,550,100]},{"i":{"x":[0.63,0.63,0.63],"y":[1,1,1]},"o":{"x":[0.37,0.37,0.37],"y":[0,0,0]},"t":133,"s":[400,400,100]},{"i":{"x":[0.63,0.63,0.63],"y":[1,1,1]},"o":{"x":[0.37,0.37,0.37],"y":[0,0,0]},"t":143,"s":[550,550,100]},{"t":150.000006109625,"s":[0,0,100]}],"ix":6,"l":2}},"ao":0,"shapes":[{"ty":"gr","it":[{"ind":0,"ty":"sh","ix":1,"ks":{"a":0,"k":{"i":[[0.185,0],[0,0],[0.121,0.142],[0,0],[-0.268,0.229],[-0.229,-0.267],[0,0],[0,0],[-0.267,-0.229],[0.229,-0.266],[0,0]],"o":[[0,0],[-0.187,0],[0,0],[-0.228,-0.266],[0.268,-0.23],[0,0],[0,0],[0.23,-0.265],[0.267,0.23],[0,0],[-0.12,0.14]],"v":[[-1.518,4.594],[-1.518,4.594],[-2.003,4.372],[-5.719,0.036],[-5.65,-0.861],[-4.751,-0.792],[-1.518,2.98],[4.753,-4.298],[5.652,-4.365],[5.719,-3.467],[-1.036,4.374]],"c":true},"ix":2},"nm":"Path 1","mn":"ADBE Vector Shape - Group","hd":false},{"ty":"fl","c":{"a":0,"k":[0.250999989229,0.063000002094,0.286000001197,1],"ix":4,"x":"var $bm_rt;\ntry {\n    $bm_rt = thisComp.layer('Controller').effect('Color')('ADBE Color Control-0001');\n} catch (e) {\n    $bm_rt = value;\n}"},"o":{"a":0,"k":100,"ix":5},"r":1,"bm":0,"nm":"Fill 1","mn":"ADBE Vector Graphic - Fill","hd":false},{"ty":"tr","p":{"a":0,"k":[32.65,8.576],"ix":2},"a":{"a":0,"k":[0,0],"ix":1},"s":{"a":0,"k":[100,100],"ix":3},"r":{"a":0,"k":0,"ix":6},"o":{"a":0,"k":100,"ix":7},"sk":{"a":0,"k":0,"ix":4},"sa":{"a":0,"k":0,"ix":5},"nm":"Transformar"}],"nm":"Group 1","np":2,"cix":2,"bm":0,"ix":1,"mn":"ADBE Vector Group","hd":false}],"ip":0,"op":150.000006109625,"st":0,"ct":1,"bm":0},{"ddd":0,"ind":3,"ty":4,"nm":"Layer 20 Outlines - Group 2 :M","parent":10,"sr":1,"ks":{"o":{"a":0,"k":100,"ix":11},"r":{"a":0,"k":0,"ix":10},"p":{"a":0,"k":[249.999,199.284,0],"ix":2,"l":2},"a":{"a":0,"k":[249.999,199.284,0],"ix":1,"l":2},"s":{"a":1,"k":[{"i":{"x":[0.63,0.63,0.63],"y":[1,1,1]},"o":{"x":[0.37,0.37,0.37],"y":[0,0,0]},"t":35,"s":[0,0,100]},{"i":{"x":[0.63,0.63,0.63],"y":[1,1,1]},"o":{"x":[0.37,0.37,0.37],"y":[0,0,0]},"t":45,"s":[110,110,100]},{"i":{"x":[0.63,0.63,0.63],"y":[1,1,1]},"o":{"x":[0.37,0.37,0.37],"y":[0,0,0]},"t":55,"s":[90,90,100]},{"i":{"x":[0.63,0.63,0.63],"y":[1,1,1]},"o":{"x":[0.37,0.37,0.37],"y":[0,0,0]},"t":65,"s":[120,120,100]},{"i":{"x":[0.63,0.63,0.63],"y":[1,1,1]},"o":{"x":[0.37,0.37,0.37],"y":[0,0,0]},"t":75,"s":[0,0,100]},{"i":{"x":[0.63,0.63,0.63],"y":[1,1,1]},"o":{"x":[0.37,0.37,0.37],"y":[0,0,0]},"t":110,"s":[0,0,100]},{"i":{"x":[0.63,0.63,0.63],"y":[1,1,1]},"o":{"x":[0.37,0.37,0.37],"y":[0,0,0]},"t":120,"s":[110,110,100]},{"i":{"x":[0.63,0.63,0.63],"y":[1,1,1]},"o":{"x":[0.37,0.37,0.37],"y":[0,0,0]},"t":130,"s":[90,90,100]},{"i":{"x":[0.63,0.63,0.63],"y":[1,1,1]},"o":{"x":[0.37,0.37,0.37],"y":[0,0,0]},"t":140,"s":[120,120,100]},{"t":150.000006109625,"s":[0,0,100]}],"ix":6,"l":2}},"ao":0,"shapes":[{"ty":"gr","it":[{"ty":"gr","it":[{"ind":0,"ty":"sh","ix":1,"ks":{"a":0,"k":{"i":[[0,0],[0,0],[-0.122,-0.141],[0,0],[0,0],[-0.185,0],[0,0],[0,0],[0,0]],"o":[[0,0],[0.186,0],[0,0],[0,0],[0.121,-0.141],[0,0],[0,0],[0,0],[0,0]],"v":[[-10.144,2.792],[-5.881,2.792],[-5.397,3.016],[0.002,9.314],[5.428,3.014],[5.911,2.792],[10.144,2.792],[10.144,-9.655],[-10.144,-9.655]],"c":true},"ix":2},"nm":"Path 1","mn":"ADBE Vector Shape - Group","hd":false},{"ind":1,"ty":"sh","ix":2,"ks":{"a":0,"k":{"i":[[0.185,0],[0,0],[0.121,0.142],[0,0],[0,0],[0,0.352],[0,0],[-0.352,0],[0,0],[0,-0.352],[0,0],[0.352,0],[0,0],[0,0]],"o":[[0,0],[-0.187,0],[0,0],[0,0],[-0.352,0],[0,0],[0,-0.352],[0,0],[0.352,0],[0,0],[0,0.352],[0,0],[0,0],[-0.121,0.141]],"v":[[0.001,10.928],[0.001,10.928],[-0.483,10.706],[-6.174,4.066],[-10.781,4.066],[-11.418,3.43],[-11.418,-10.292],[-10.781,-10.928],[10.781,-10.928],[11.418,-10.292],[11.418,3.43],[10.781,4.066],[6.203,4.066],[0.484,10.706]],"c":true},"ix":2},"nm":"Path 2","mn":"ADBE Vector Shape - Group","hd":false},{"ty":"mm","mm":1,"nm":"Merge Paths 1","mn":"ADBE Vector Filter - Merge","hd":false},{"ty":"fl","c":{"a":0,"k":[0.250999987125,0.063000001013,0.286000013351,1],"ix":4,"x":"var $bm_rt;\ntry {\n    $bm_rt = thisComp.layer('Controller')('Effects')('Color')('ADBE Color Control-0001');\n} catch (e) {\n    $bm_rt = value;\n}"},"o":{"a":0,"k":100,"ix":5},"r":1,"bm":0,"nm":"Fill 1","mn":"ADBE Vector Graphic - Fill","hd":false},{"ty":"tr","p":{"a":0,"k":[32.25,11.179],"ix":2},"a":{"a":0,"k":[0,0],"ix":1},"s":{"a":0,"k":[100,100],"ix":3},"r":{"a":0,"k":0,"ix":6},"o":{"a":0,"k":100,"ix":7},"sk":{"a":0,"k":0,"ix":4},"sa":{"a":0,"k":0,"ix":5},"nm":"Transformar"}],"nm":"Group 2","np":4,"cix":2,"bm":0,"ix":1,"mn":"ADBE Vector Group","hd":false},{"ty":"tr","p":{"a":0,"k":[249.999,144.642],"ix":2},"a":{"a":0,"k":[32.25,11.179],"ix":1},"s":{"a":0,"k":[500,500],"ix":3},"r":{"a":0,"k":0,"ix":6},"o":{"a":0,"k":100,"ix":7},"sk":{"a":0,"k":0,"ix":4},"sa":{"a":0,"k":0,"ix":5},"nm":"Transformar"}],"nm":"Layer 20 Outlines - Group 2","np":1,"cix":2,"bm":0,"ix":1,"mn":"ADBE Vector Group","hd":false},{"ty":"gr","it":[{"ty":"gr","it":[{"ind":0,"ty":"sh","ix":1,"ks":{"a":0,"k":{"i":[[0,0],[0,0],[0,0],[0,0],[0,0],[0,0],[0,0]],"o":[[0,0],[0,0],[0,0],[0,0],[0,0],[0,0],[0,0]],"v":[[10.781,1.47],[5.911,1.47],[0.001,8.331],[-5.881,1.47],[-10.781,1.47],[-10.781,-8.331],[10.781,-8.331]],"c":true},"ix":2},"nm":"Path 1","mn":"ADBE Vector Shape - Group","hd":false},{"ty":"fl","c":{"a":0,"k":[0.96899998188,0.889999985695,0.493999987841,1],"ix":4,"x":"var $bm_rt;\ntry {\n    $bm_rt = thisComp.layer('Controller').effect('Color 2')('ADBE Color Control-0001');\n} catch (e) {\n    $bm_rt = value;\n}"},"o":{"a":0,"k":100,"ix":5},"r":1,"bm":0,"nm":"Fill 1","mn":"ADBE Vector Graphic - Fill","hd":false},{"ty":"tr","p":{"a":0,"k":[32.251,13.138],"ix":2},"a":{"a":0,"k":[0,0],"ix":1},"s":{"a":0,"k":[100,100],"ix":3},"r":{"a":0,"k":0,"ix":6},"o":{"a":0,"k":100,"ix":7},"sk":{"a":0,"k":0,"ix":4},"sa":{"a":0,"k":0,"ix":5},"nm":"Transformar"}],"nm":"Group 3","np":2,"cix":2,"bm":0,"ix":1,"mn":"ADBE Vector Group","hd":false},{"ty":"tr","p":{"a":0,"k":[250.001,154.438],"ix":2},"a":{"a":0,"k":[32.251,13.138],"ix":1},"s":{"a":0,"k":[500,500],"ix":3},"r":{"a":0,"k":0,"ix":6},"o":{"a":0,"k":100,"ix":7},"sk":{"a":0,"k":0,"ix":4},"sa":{"a":0,"k":0,"ix":5},"nm":"Transformar"}],"nm":"Layer 20 Outlines - Group 3","np":1,"cix":2,"bm":0,"ix":2,"mn":"ADBE Vector Group","hd":false},{"ty":"gr","it":[{"ty":"gr","it":[{"ind":0,"ty":"sh","ix":1,"ks":{"a":0,"k":{"i":[[0,0],[0,0],[0,0],[0,0],[0,0],[0,0],[0,0]],"o":[[0,0],[0,0],[0,0],[0,0],[0,0],[0,0],[0,0]],"v":[[10.781,3.43],[5.911,3.43],[0.001,10.291],[-5.881,3.43],[-10.781,3.43],[-10.781,-10.291],[10.781,-10.291]],"c":true},"ix":2},"nm":"Path 1","mn":"ADBE Vector Shape - Group","hd":false},{"ty":"fl","c":{"a":0,"k":[0.944999992847,0.808000028133,0.203999996185,1],"ix":4,"x":"var $bm_rt;\ntry {\n    $bm_rt = thisComp.layer('Controller').effect('Color 3')('ADBE Color Control-0001');\n} catch (e) {\n    $bm_rt = value;\n}"},"o":{"a":0,"k":100,"ix":5},"r":1,"bm":0,"nm":"Fill 1","mn":"ADBE Vector Graphic - Fill","hd":false},{"ty":"tr","p":{"a":0,"k":[32.251,11.178],"ix":2},"a":{"a":0,"k":[0,0],"ix":1},"s":{"a":0,"k":[100,100],"ix":3},"r":{"a":0,"k":0,"ix":6},"o":{"a":0,"k":100,"ix":7},"sk":{"a":0,"k":0,"ix":4},"sa":{"a":0,"k":0,"ix":5},"nm":"Transformar"}],"nm":"Group 4","np":2,"cix":2,"bm":0,"ix":1,"mn":"ADBE Vector Group","hd":false},{"ty":"tr","p":{"a":0,"k":[250.001,144.638],"ix":2},"a":{"a":0,"k":[32.251,11.178],"ix":1},"s":{"a":0,"k":[500,500],"ix":3},"r":{"a":0,"k":0,"ix":6},"o":{"a":0,"k":100,"ix":7},"sk":{"a":0,"k":0,"ix":4},"sa":{"a":0,"k":0,"ix":5},"nm":"Transformar"}],"nm":"Layer 20 Outlines - Group 4","np":1,"cix":2,"bm":0,"ix":3,"mn":"ADBE Vector Group","hd":false}],"ip":0,"op":150.000006109625,"st":0,"ct":1,"bm":0},{"ddd":0,"ind":4,"ty":4,"nm":"Layer 20 Outlines - Group 26 :M 2","parent":10,"sr":1,"ks":{"o":{"a":0,"k":100,"ix":11},"r":{"a":0,"k":0,"ix":10},"p":{"a":0,"k":[250.001,264.708,0],"ix":2,"l":2},"a":{"a":0,"k":[250.001,264.708,0],"ix":1,"l":2},"s":{"a":0,"k":[100,100,100],"ix":6,"l":2}},"ao":0,"shapes":[{"ty":"gr","it":[{"ty":"gr","it":[{"ind":0,"ty":"sh","ix":1,"ks":{"a":0,"k":{"i":[[0.352,0],[0,0.352],[0,0],[3.972,0],[0,0],[0,0.352],[-0.352,0],[0,0],[0,-4.675],[0,0]],"o":[[-0.352,0],[0,0],[0,-3.971],[0,0],[-0.352,0],[0,-0.351],[0,0],[4.674,0],[0,0],[0,0.352]],"v":[[21.072,19.826],[20.435,19.189],[20.435,-11.349],[13.231,-18.553],[-21.072,-18.553],[-21.709,-19.19],[-21.072,-19.826],[13.231,-19.826],[21.709,-11.349],[21.709,19.189]],"c":true},"ix":2},"nm":"Path 1","mn":"ADBE Vector Shape - Group","hd":false},{"ty":"fl","c":{"a":0,"k":[0.250999987125,0.063000001013,0.286000013351,1],"ix":4,"x":"var $bm_rt;\ntry {\n    $bm_rt = thisComp.layer('Controller')('Effects')('Color')('ADBE Color Control-0001');\n} catch (e) {\n    $bm_rt = value;\n}"},"o":{"a":0,"k":100,"ix":5},"r":1,"bm":0,"nm":"Fill 1","mn":"ADBE Vector Graphic - Fill","hd":false},{"ty":"tr","p":{"a":0,"k":[42.542,25.959],"ix":2},"a":{"a":0,"k":[0,0],"ix":1},"s":{"a":0,"k":[100,100],"ix":3},"r":{"a":0,"k":0,"ix":6},"o":{"a":0,"k":100,"ix":7},"sk":{"a":0,"k":0,"ix":4},"sa":{"a":0,"k":0,"ix":5},"nm":"Transformar"}],"nm":"Group 26","np":2,"cix":2,"bm":0,"ix":1,"mn":"ADBE Vector Group","hd":false},{"ty":"tr","p":{"a":0,"k":[301.456,218.546],"ix":2},"a":{"a":0,"k":[42.542,25.959],"ix":1},"s":{"a":0,"k":[500,500],"ix":3},"r":{"a":0,"k":0,"ix":6},"o":{"a":0,"k":100,"ix":7},"sk":{"a":0,"k":0,"ix":4},"sa":{"a":0,"k":0,"ix":5},"nm":"Transformar"}],"nm":"Layer 20 Outlines - Group 226","np":1,"cix":2,"bm":0,"ix":1,"mn":"ADBE Vector Group","hd":false},{"ty":"gr","it":[{"ty":"gr","it":[{"ind":0,"ty":"sh","ix":1,"ks":{"a":0,"k":{"i":[[4.674,0],[0,0],[0,0.352],[-0.351,0],[0,0],[0,3.971],[0,0],[-0.352,0],[0,-0.351],[0,0]],"o":[[0,0],[-0.351,0],[0,-0.351],[0,0],[3.972,0],[0,0],[0,-0.351],[0.351,0],[0,0],[0,4.674]],"v":[[13.949,7.909],[-21.791,7.909],[-22.427,7.272],[-21.791,6.636],[13.949,6.636],[21.153,-0.568],[21.153,-7.273],[21.79,-7.909],[22.427,-7.273],[22.427,-0.568]],"c":true},"ix":2},"nm":"Path 1","mn":"ADBE Vector Shape - Group","hd":false},{"ty":"fl","c":{"a":0,"k":[0.250999987125,0.063000001013,0.286000013351,1],"ix":4,"x":"var $bm_rt;\ntry {\n    $bm_rt = thisComp.layer('Controller')('Effects')('Color')('ADBE Color Control-0001');\n} catch (e) {\n    $bm_rt = value;\n}"},"o":{"a":0,"k":100,"ix":5},"r":1,"bm":0,"nm":"Fill 1","mn":"ADBE Vector Graphic - Fill","hd":false},{"ty":"tr","p":{"a":0,"k":[41.824,56.341],"ix":2},"a":{"a":0,"k":[0,0],"ix":1},"s":{"a":0,"k":[100,100],"ix":3},"r":{"a":0,"k":0,"ix":6},"o":{"a":0,"k":100,"ix":7},"sk":{"a":0,"k":0,"ix":4},"sa":{"a":0,"k":0,"ix":5},"nm":"Transformar"}],"nm":"Group 27","np":2,"cix":2,"bm":0,"ix":1,"mn":"ADBE Vector Group","hd":false},{"ty":"tr","p":{"a":0,"k":[297.867,370.456],"ix":2},"a":{"a":0,"k":[41.824,56.341],"ix":1},"s":{"a":0,"k":[500,500],"ix":3},"r":{"a":0,"k":0,"ix":6},"o":{"a":0,"k":100,"ix":7},"sk":{"a":0,"k":0,"ix":4},"sa":{"a":0,"k":0,"ix":5},"nm":"Transformar"}],"nm":"Layer 20 Outlines - Group 227","np":1,"cix":2,"bm":0,"ix":2,"mn":"ADBE Vector Group","hd":false},{"ty":"gr","it":[{"ty":"gr","it":[{"ind":0,"ty":"sh","ix":1,"ks":{"a":0,"k":{"i":[[0.352,0],[0,0],[0,4.674],[0,0],[-4.674,0],[0,0],[0,-0.352],[0.352,0],[0,0],[0,-3.971],[0,0],[-3.971,0],[0,0],[0,-0.351]],"o":[[0,0],[-4.674,0],[0,0],[0,-4.674],[0,0],[0.352,0],[0,0.351],[0,0],[-3.971,0],[0,0],[0,3.971],[0,0],[0.352,0],[0,0.352]],"v":[[6.894,29.058],[-0.491,29.058],[-8.968,20.581],[-8.968,-20.581],[-0.491,-29.058],[8.331,-29.058],[8.968,-28.421],[8.331,-27.786],[-0.491,-27.786],[-7.694,-20.581],[-7.694,20.581],[-0.491,27.786],[6.894,27.786],[7.531,28.421]],"c":true},"ix":2},"nm":"Path 1","mn":"ADBE Vector Shape - Group","hd":false},{"ty":"fl","c":{"a":0,"k":[0.250999987125,0.063000001013,0.286000013351,1],"ix":4,"x":"var $bm_rt;\ntry {\n    $bm_rt = thisComp.layer('Controller')('Effects')('Color')('ADBE Color Control-0001');\n} catch (e) {\n    $bm_rt = value;\n}"},"o":{"a":0,"k":100,"ix":5},"r":1,"bm":0,"nm":"Fill 1","mn":"ADBE Vector Graphic - Fill","hd":false},{"ty":"tr","p":{"a":0,"k":[9.219,35.192],"ix":2},"a":{"a":0,"k":[0,0],"ix":1},"s":{"a":0,"k":[100,100],"ix":3},"r":{"a":0,"k":0,"ix":6},"o":{"a":0,"k":100,"ix":7},"sk":{"a":0,"k":0,"ix":4},"sa":{"a":0,"k":0,"ix":5},"nm":"Transformar"}],"nm":"Group 28","np":2,"cix":2,"bm":0,"ix":1,"mn":"ADBE Vector Group","hd":false},{"ty":"tr","p":{"a":0,"k":[134.841,264.708],"ix":2},"a":{"a":0,"k":[9.219,35.192],"ix":1},"s":{"a":0,"k":[500,500],"ix":3},"r":{"a":0,"k":0,"ix":6},"o":{"a":0,"k":100,"ix":7},"sk":{"a":0,"k":0,"ix":4},"sa":{"a":0,"k":0,"ix":5},"nm":"Transformar"}],"nm":"Layer 20 Outlines - Group 228","np":1,"cix":2,"bm":0,"ix":3,"mn":"ADBE Vector Group","hd":false}],"ip":0,"op":150.000006109625,"st":0,"ct":1,"bm":0},{"ddd":0,"ind":5,"ty":4,"nm":"Layer 20 Outlines - Group 13 :M","parent":9,"sr":1,"ks":{"o":{"a":0,"k":100,"ix":11},"r":{"a":0,"k":0,"ix":10},"p":{"a":0,"k":[263.952,209.667,0],"ix":2,"l":2},"a":{"a":0,"k":[263.952,209.667,0],"ix":1,"l":2},"s":{"a":0,"k":[100,100,100],"ix":6,"l":2}},"ao":0,"shapes":[{"ty":"gr","it":[{"ty":"gr","it":[{"ind":0,"ty":"sh","ix":1,"ks":{"a":0,"k":{"i":[[0.745,0],[0.488,0.181],[0.429,1.234],[-1.854,1.072],[0,0],[-1.834,-0.492],[0,0],[-0.582,0.264],[-0.165,-0.284],[0,0],[0.305,-0.177],[0.176,0.306],[0,0],[1.474,0.435],[0,0],[1.352,-0.78],[0,0],[-0.469,-1.349],[-0.861,-0.32],[-0.785,0.454],[0,0],[-3.544,-1.769],[0.157,-0.314],[0.313,0.157],[1.675,-0.967],[0,0]],"o":[[-0.506,0],[-1.206,-0.45],[-0.669,-1.926],[0,0],[1.648,-0.95],[0,0],[1.315,0.387],[0.296,-0.138],[0,0],[0.176,0.305],[-0.305,0.175],[0,0],[-0.85,0.301],[0,0],[-1.507,-0.404],[0,0],[-1.326,0.766],[0.308,0.887],[0.851,0.317],[0,0],[1.8,-1.039],[0.315,0.157],[-0.157,0.315],[-2.966,-1.478],[0,0],[-0.664,0.384]],"v":[[-8.085,6.603],[-9.587,6.332],[-12.16,3.682],[-10.113,-1.491],[-3.341,-5.4],[2.057,-6.111],[6.785,-4.844],[10.477,-5.324],[11.292,-5.064],[12.653,-2.707],[12.42,-1.835],[11.549,-2.07],[10.463,-3.951],[6.439,-3.618],[1.729,-4.88],[-2.704,-4.296],[-9.477,-0.387],[-10.956,3.264],[-9.143,5.137],[-6.57,4.92],[-2.693,2.682],[5.458,2.236],[5.743,3.09],[4.89,3.375],[-2.055,3.786],[-5.934,6.024]],"c":true},"ix":2},"nm":"Path 1","mn":"ADBE Vector Shape - Group","hd":false},{"ty":"fl","c":{"a":0,"k":[0.250999987125,0.063000001013,0.286000013351,1],"ix":4,"x":"var $bm_rt;\ntry {\n    $bm_rt = thisComp.layer('Controller')('Effects')('Color')('ADBE Color Control-0001');\n} catch (e) {\n    $bm_rt = value;\n}"},"o":{"a":0,"k":100,"ix":5},"r":1,"bm":0,"nm":"Fill 1","mn":"ADBE Vector Graphic - Fill","hd":false},{"ty":"tr","p":{"a":0,"k":[34.864,24.06],"ix":2},"a":{"a":0,"k":[0,0],"ix":1},"s":{"a":0,"k":[100,100],"ix":3},"r":{"a":0,"k":0,"ix":6},"o":{"a":0,"k":100,"ix":7},"sk":{"a":0,"k":0,"ix":4},"sa":{"a":0,"k":0,"ix":5},"nm":"Transformar"}],"nm":"Group 13","np":2,"cix":2,"bm":0,"ix":1,"mn":"ADBE Vector Group","hd":false},{"ty":"tr","p":{"a":0,"k":[263.952,209.667],"ix":2},"a":{"a":0,"k":[35.041,24.184],"ix":1},"s":{"a":0,"k":[500,500],"ix":3},"r":{"a":0,"k":0,"ix":6},"o":{"a":0,"k":100,"ix":7},"sk":{"a":0,"k":0,"ix":4},"sa":{"a":0,"k":0,"ix":5},"nm":"Transformar"}],"nm":"Layer 20 Outlines - Group 113","np":1,"cix":2,"bm":0,"ix":1,"mn":"ADBE Vector Group","hd":false},{"ty":"gr","it":[{"ty":"gr","it":[{"ind":0,"ty":"sh","ix":1,"ks":{"a":0,"k":{"i":[[0,0],[1.817,0.534],[0,0],[1.488,-0.858],[0,0],[-0.581,-1.675],[-1.96,1.132],[0,0],[-3.031,-1.512],[0,0]],"o":[[0,0],[0,0],[-1.66,-0.444],[0,0],[-1.535,0.886],[0.781,2.25],[0,0],[2.045,-1.18],[0,0],[0,0]],"v":[[10.759,-5.078],[6.638,-4.561],[1.912,-5.828],[-3.004,-5.181],[-9.776,-1.271],[-11.539,3.141],[-6.233,5.141],[-2.355,2.901],[5.193,2.473],[12.12,-2.721]],"c":true},"ix":2},"nm":"Path 1","mn":"ADBE Vector Shape - Group","hd":false},{"ty":"fl","c":{"a":0,"k":[0.776000022888,0.600000023842,0.458999991417,1],"ix":4,"x":"var $bm_rt;\ntry {\n    $bm_rt = thisComp.layer('Controller').effect('Color 4')('ADBE Color Control-0001');\n} catch (e) {\n    $bm_rt = value;\n}"},"o":{"a":0,"k":100,"ix":5},"r":1,"bm":0,"nm":"Fill 1","mn":"ADBE Vector Graphic - Fill","hd":false},{"ty":"tr","p":{"a":0,"k":[34.845,24.393],"ix":2},"a":{"a":0,"k":[0,0],"ix":1},"s":{"a":0,"k":[100,100],"ix":3},"r":{"a":0,"k":0,"ix":6},"o":{"a":0,"k":100,"ix":7},"sk":{"a":0,"k":0,"ix":4},"sa":{"a":0,"k":0,"ix":5},"nm":"Transformar"}],"nm":"Group 14","np":2,"cix":2,"bm":0,"ix":1,"mn":"ADBE Vector Group","hd":false},{"ty":"tr","p":{"a":0,"k":[263.955,209.676],"ix":2},"a":{"a":0,"k":[35.041,24.185],"ix":1},"s":{"a":0,"k":[500,500],"ix":3},"r":{"a":0,"k":0,"ix":6},"o":{"a":0,"k":100,"ix":7},"sk":{"a":0,"k":0,"ix":4},"sa":{"a":0,"k":0,"ix":5},"nm":"Transformar"}],"nm":"Layer 20 Outlines - Group 114","np":1,"cix":2,"bm":0,"ix":2,"mn":"ADBE Vector Group","hd":false}],"ip":0,"op":150.000006109625,"st":0,"ct":1,"bm":0},{"ddd":0,"ind":6,"ty":4,"nm":"Layer 20 Outlines - Group 26 :M 4","parent":10,"td":1,"sr":1,"ks":{"o":{"a":0,"k":100,"ix":11},"r":{"a":0,"k":0,"ix":10},"p":{"a":0,"k":[250.001,264.708,0],"ix":2,"l":2},"a":{"a":0,"k":[250.001,264.708,0],"ix":1,"l":2},"s":{"a":0,"k":[100,100,100],"ix":6,"l":2}},"ao":0,"shapes":[{"ty":"gr","it":[{"ty":"gr","it":[{"ind":0,"ty":"sh","ix":1,"ks":{"a":0,"k":{"i":[[4.418,0],[0,0],[0,4.418],[0,0],[-4.419,0],[0,0],[0,-4.418],[0,0]],"o":[[0,0],[-4.419,0],[0,0],[0,-4.418],[0,0],[4.418,0],[0,0],[0,4.418]],"v":[[23.363,28.422],[-23.363,28.422],[-31.363,20.422],[-31.363,-20.422],[-23.363,-28.422],[23.363,-28.422],[31.363,-20.422],[31.363,20.422]],"c":true},"ix":2},"nm":"Path 1","mn":"ADBE Vector Shape - Group","hd":false},{"ty":"fl","c":{"a":0,"k":[1,1,1,1],"ix":4,"x":"var $bm_rt;\ntry {\n    $bm_rt = thisComp.layer('Controller').effect('Color 5')('ADBE Color Control-0001');\n} catch (e) {\n    $bm_rt = value;\n}"},"o":{"a":0,"k":100,"ix":5},"r":1,"bm":0,"nm":"Fill 1","mn":"ADBE Vector Graphic - Fill","hd":false},{"ty":"tr","p":{"a":0,"k":[32.251,35.192],"ix":2},"a":{"a":0,"k":[0,0],"ix":1},"s":{"a":0,"k":[100,100],"ix":3},"r":{"a":0,"k":0,"ix":6},"o":{"a":0,"k":100,"ix":7},"sk":{"a":0,"k":0,"ix":4},"sa":{"a":0,"k":0,"ix":5},"nm":"Transformar"}],"nm":"Group 31","np":2,"cix":2,"bm":0,"ix":1,"mn":"ADBE Vector Group","hd":false},{"ty":"tr","p":{"a":0,"k":[250.001,264.707],"ix":2},"a":{"a":0,"k":[32.251,35.192],"ix":1},"s":{"a":0,"k":[500,500],"ix":3},"r":{"a":0,"k":0,"ix":6},"o":{"a":0,"k":100,"ix":7},"sk":{"a":0,"k":0,"ix":4},"sa":{"a":0,"k":0,"ix":5},"nm":"Transformar"}],"nm":"Layer 20 Outlines - Group 331","np":1,"cix":2,"bm":0,"ix":1,"mn":"ADBE Vector Group","hd":false}],"ip":0,"op":150.000006109625,"st":0,"ct":1,"bm":0},{"ddd":0,"ind":7,"ty":4,"nm":"Layer 20 Outlines - Group 7 :M","parent":10,"tt":1,"tp":6,"sr":1,"ks":{"o":{"a":0,"k":100,"ix":11},"r":{"a":1,"k":[{"i":{"x":[0.63],"y":[1]},"o":{"x":[0.37],"y":[0]},"t":5,"s":[0]},{"i":{"x":[0.63],"y":[1]},"o":{"x":[0.37],"y":[0]},"t":20,"s":[-8]},{"i":{"x":[0.63],"y":[1]},"o":{"x":[0.37],"y":[0]},"t":35,"s":[6]},{"i":{"x":[0.833],"y":[1]},"o":{"x":[0.167],"y":[0]},"t":50,"s":[0]},{"i":{"x":[0.63],"y":[1]},"o":{"x":[0.37],"y":[0]},"t":80,"s":[0]},{"i":{"x":[0.63],"y":[1]},"o":{"x":[0.37],"y":[0]},"t":95,"s":[-8]},{"i":{"x":[0.63],"y":[1]},"o":{"x":[0.37],"y":[0]},"t":110,"s":[6]},{"t":125.000005091354,"s":[0]}],"ix":10},"p":{"a":1,"k":[{"i":{"x":0.63,"y":1},"o":{"x":0.37,"y":0},"t":0,"s":[116.084,207.63,0],"to":[-3.073,-0.591,0],"ti":[0,0,0]},{"i":{"x":0.63,"y":1},"o":{"x":0.37,"y":0},"t":15,"s":[97.645,204.084,0],"to":[0,0,0],"ti":[0,0,0]},{"i":{"x":0.63,"y":1},"o":{"x":0.37,"y":0},"t":30,"s":[122.089,204.084,0],"to":[0,0,0],"ti":[1.001,-0.591,0]},{"i":{"x":0.833,"y":0.833},"o":{"x":0.167,"y":0.167},"t":45,"s":[116.084,207.63,0],"to":[0,0,0],"ti":[0,0,0]},{"i":{"x":0.63,"y":1},"o":{"x":0.37,"y":0},"t":75,"s":[116.084,207.63,0],"to":[-3.073,-0.591,0],"ti":[0,0,0]},{"i":{"x":0.63,"y":1},"o":{"x":0.37,"y":0},"t":90,"s":[97.645,204.084,0],"to":[0,0,0],"ti":[0,0,0]},{"i":{"x":0.63,"y":1},"o":{"x":0.37,"y":0},"t":105,"s":[122.089,204.084,0],"to":[0,0,0],"ti":[1.001,-0.591,0]},{"t":120.0000048877,"s":[116.084,207.63,0]}],"ix":2,"l":2},"a":{"a":0,"k":[116.084,207.63,0],"ix":1,"l":2},"s":{"a":0,"k":[100,100,100],"ix":6,"l":2}},"ao":0,"shapes":[{"ty":"gr","it":[{"ty":"gr","it":[{"ind":0,"ty":"sh","ix":1,"ks":{"a":0,"k":{"i":[[0.22,0],[0.099,0.058],[0,0],[0,0.228],[0,0],[-1.331,1.541],[-0.267,-0.154],[0,0],[0.175,-0.304],[0,0],[0.305,0.176],[-0.176,0.305],[0,0],[0,0],[0,-1.548],[0,0],[0,0],[0,0],[-0.306,-0.176],[0.176,-0.305],[0,0]],"o":[[-0.108,0],[0,0],[-0.197,-0.115],[0,0],[0,-2.029],[0.199,-0.232],[0,0],[0.304,0.177],[0,0],[-0.176,0.305],[-0.305,-0.176],[0,0],[0,0],[-0.924,1.24],[0,0],[0,0],[0,0],[0.176,-0.305],[0.304,0.175],[0,0],[-0.118,0.205]],"v":[[-4.046,17.212],[-4.363,17.127],[-14.154,11.537],[-14.473,10.985],[-14.473,-13.838],[-12.409,-19.373],[-11.608,-19.508],[9.715,-7.259],[9.949,-6.388],[1.949,7.468],[1.079,7.7],[0.846,6.83],[8.527,-6.474],[-11.771,-18.132],[-13.199,-13.838],[-13.199,10.617],[-4.279,15.705],[-1.152,10.29],[-0.283,10.058],[-0.049,10.928],[-3.495,16.894]],"c":true},"ix":2},"nm":"Path 1","mn":"ADBE Vector Shape - Group","hd":false},{"ty":"fl","c":{"a":0,"k":[0.250999987125,0.063000001013,0.286000013351,1],"ix":4,"x":"var $bm_rt;\ntry {\n    $bm_rt = thisComp.layer('Controller')('Effects')('Color')('ADBE Color Control-0001');\n} catch (e) {\n    $bm_rt = value;\n}"},"o":{"a":0,"k":100,"ix":5},"r":1,"bm":0,"nm":"Fill 1","mn":"ADBE Vector Graphic - Fill","hd":false},{"ty":"tr","p":{"a":0,"k":[10.373,25.999],"ix":2},"a":{"a":0,"k":[0,0],"ix":1},"s":{"a":0,"k":[100,100],"ix":3},"r":{"a":0,"k":0,"ix":6},"o":{"a":0,"k":100,"ix":7},"sk":{"a":0,"k":0,"ix":4},"sa":{"a":0,"k":0,"ix":5},"nm":"Transformar"}],"nm":"Group 7","np":2,"cix":2,"bm":0,"ix":1,"mn":"ADBE Vector Group","hd":false},{"ty":"tr","p":{"a":0,"k":[140.39,218.915],"ix":2},"a":{"a":0,"k":[10.328,26.033],"ix":1},"s":{"a":0,"k":[500,500],"ix":3},"r":{"a":0,"k":0,"ix":6},"o":{"a":0,"k":100,"ix":7},"sk":{"a":0,"k":0,"ix":4},"sa":{"a":0,"k":0,"ix":5},"nm":"Transformar"}],"nm":"Layer 20 Outlines - Group 7","np":1,"cix":2,"bm":0,"ix":1,"mn":"ADBE Vector Group","hd":false},{"ty":"gr","it":[{"ty":"gr","it":[{"ind":0,"ty":"sh","ix":1,"ks":{"a":0,"k":{"i":[[0.586,0.338],[0.338,-0.586],[-0.586,-0.338],[-0.338,0.586]],"o":[[-0.586,-0.338],[-0.339,0.586],[0.586,0.339],[0.339,-0.586]],"v":[[0.613,-1.061],[-1.061,-0.612],[-0.613,1.06],[1.061,0.613]],"c":true},"ix":2},"nm":"Path 1","mn":"ADBE Vector Shape - Group","hd":false},{"ty":"fl","c":{"a":0,"k":[0.250999987125,0.063000001013,0.286000013351,1],"ix":4,"x":"var $bm_rt;\ntry {\n    $bm_rt = thisComp.layer('Controller')('Effects')('Color')('ADBE Color Control-0001');\n} catch (e) {\n    $bm_rt = value;\n}"},"o":{"a":0,"k":100,"ix":5},"r":1,"bm":0,"nm":"Fill 1","mn":"ADBE Vector Graphic - Fill","hd":false},{"ty":"tr","p":{"a":0,"k":[13.448,20.329],"ix":2},"a":{"a":0,"k":[0,0],"ix":1},"s":{"a":0,"k":[100,100],"ix":3},"r":{"a":0,"k":0,"ix":6},"o":{"a":0,"k":100,"ix":7},"sk":{"a":0,"k":0,"ix":4},"sa":{"a":0,"k":0,"ix":5},"nm":"Transformar"}],"nm":"Group 8","np":2,"cix":2,"bm":0,"ix":1,"mn":"ADBE Vector Group","hd":false},{"ty":"tr","p":{"a":0,"k":[155.99,190.393],"ix":2},"a":{"a":0,"k":[13.448,20.329],"ix":1},"s":{"a":0,"k":[500,500],"ix":3},"r":{"a":0,"k":0,"ix":6},"o":{"a":0,"k":100,"ix":7},"sk":{"a":0,"k":0,"ix":4},"sa":{"a":0,"k":0,"ix":5},"nm":"Transformar"}],"nm":"Layer 20 Outlines - Group 8","np":1,"cix":2,"bm":0,"ix":2,"mn":"ADBE Vector Group","hd":false},{"ty":"gr","it":[{"ty":"gr","it":[{"ind":0,"ty":"sh","ix":1,"ks":{"a":0,"k":{"i":[[0,0],[0,0],[0,0],[0,0]],"o":[[0,0],[0,0],[0,0],[0,0]],"v":[[-13.591,8.461],[-4.001,14.091],[9.441,-9.191],[-0.246,-14.791]],"c":true},"ix":2},"nm":"Path 1","mn":"ADBE Vector Shape - Group","hd":false},{"ty":"fl","c":{"a":0,"k":[0.624000012875,0.882000029087,0.991999983788,1],"ix":4,"x":"var $bm_rt;\ntry {\n    $bm_rt = thisComp.layer('Controller').effect('Color 6')('ADBE Color Control-0001');\n} catch (e) {\n    $bm_rt = value;\n}"},"o":{"a":0,"k":100,"ix":5},"r":1,"bm":0,"nm":"Fill 1","mn":"ADBE Vector Graphic - Fill","hd":false},{"ty":"tr","p":{"a":0,"k":[10.328,28.484],"ix":2},"a":{"a":0,"k":[0,0],"ix":1},"s":{"a":0,"k":[100,100],"ix":3},"r":{"a":0,"k":0,"ix":6},"o":{"a":0,"k":100,"ix":7},"sk":{"a":0,"k":0,"ix":4},"sa":{"a":0,"k":0,"ix":5},"nm":"Transformar"}],"nm":"Group 11","np":2,"cix":2,"bm":0,"ix":1,"mn":"ADBE Vector Group","hd":false},{"ty":"tr","p":{"a":0,"k":[140.391,231.168],"ix":2},"a":{"a":0,"k":[10.328,28.484],"ix":1},"s":{"a":0,"k":[500,500],"ix":3},"r":{"a":0,"k":0,"ix":6},"o":{"a":0,"k":100,"ix":7},"sk":{"a":0,"k":0,"ix":4},"sa":{"a":0,"k":0,"ix":5},"nm":"Transformar"}],"nm":"Layer 20 Outlines - Group 111","np":1,"cix":2,"bm":0,"ix":3,"mn":"ADBE Vector Group","hd":false},{"ty":"gr","it":[{"ty":"gr","it":[{"ind":0,"ty":"sh","ix":1,"ks":{"a":0,"k":{"i":[[0,0],[0,-1.959],[0,0],[0,0]],"o":[[-2.346,2.208],[0,0],[0,0],[0,0]],"v":[[-7.488,-13.751],[-9.497,-6.582],[-9.297,16.101],[4.197,-7.201]],"c":true},"ix":2},"nm":"Path 1","mn":"ADBE Vector Shape - Group","hd":false},{"ty":"fl","c":{"a":0,"k":[0.47499999404,0.764999985695,0.987999975681,1],"ix":4,"x":"var $bm_rt;\ntry {\n    $bm_rt = thisComp.layer('Controller').effect('Color 7')('ADBE Color Control-0001');\n} catch (e) {\n    $bm_rt = value;\n}"},"o":{"a":0,"k":100,"ix":5},"r":1,"bm":0,"nm":"Fill 1","mn":"ADBE Vector Graphic - Fill","hd":false},{"ty":"tr","p":{"a":0,"k":[6.085,20.943],"ix":2},"a":{"a":0,"k":[0,0],"ix":1},"s":{"a":0,"k":[100,100],"ix":3},"r":{"a":0,"k":0,"ix":6},"o":{"a":0,"k":100,"ix":7},"sk":{"a":0,"k":0,"ix":4},"sa":{"a":0,"k":0,"ix":5},"nm":"Transformar"}],"nm":"Group 12","np":2,"cix":2,"bm":0,"ix":1,"mn":"ADBE Vector Group","hd":false},{"ty":"tr","p":{"a":0,"k":[119.171,193.466],"ix":2},"a":{"a":0,"k":[6.085,20.943],"ix":1},"s":{"a":0,"k":[500,500],"ix":3},"r":{"a":0,"k":0,"ix":6},"o":{"a":0,"k":100,"ix":7},"sk":{"a":0,"k":0,"ix":4},"sa":{"a":0,"k":0,"ix":5},"nm":"Transformar"}],"nm":"Layer 20 Outlines - Group 112","np":1,"cix":2,"bm":0,"ix":4,"mn":"ADBE Vector Group","hd":false},{"ty":"gr","it":[{"ty":"gr","it":[{"ind":0,"ty":"sh","ix":1,"ks":{"a":0,"k":{"i":[[0.22,0],[0.1,0.058],[0,0],[-0.176,0.304],[-0.306,-0.177],[0,0],[0.176,-0.305]],"o":[[-0.108,0],[0,0],[-0.305,-0.177],[0.176,-0.305],[0,0],[0.305,0.175],[-0.118,0.204]],"v":[[5.768,4.013],[5.45,3.928],[-6.087,-2.732],[-6.32,-3.603],[-5.45,-3.836],[6.087,2.825],[6.32,3.695]],"c":true},"ix":2},"nm":"Path 1","mn":"ADBE Vector Shape - Group","hd":false},{"ty":"fl","c":{"a":0,"k":[0.250999987125,0.063000001013,0.286000013351,1],"ix":4,"x":"var $bm_rt;\ntry {\n    $bm_rt = thisComp.layer('Controller')('Effects')('Color')('ADBE Color Control-0001');\n} catch (e) {\n    $bm_rt = value;\n}"},"o":{"a":0,"k":100,"ix":5},"r":1,"bm":0,"nm":"Fill 1","mn":"ADBE Vector Graphic - Fill","hd":false},{"ty":"tr","p":{"a":0,"k":[42.445,41.107],"ix":2},"a":{"a":0,"k":[0,0],"ix":1},"s":{"a":0,"k":[100,100],"ix":3},"r":{"a":0,"k":0,"ix":6},"o":{"a":0,"k":100,"ix":7},"sk":{"a":0,"k":0,"ix":4},"sa":{"a":0,"k":0,"ix":5},"nm":"Transformar"}],"nm":"Group 15","np":2,"cix":2,"bm":0,"ix":1,"mn":"ADBE Vector Group","hd":false},{"ty":"tr","p":{"a":0,"k":[300.971,294.514],"ix":2},"a":{"a":0,"k":[42.445,41.153],"ix":1},"s":{"a":0,"k":[500,500],"ix":3},"r":{"a":0,"k":0,"ix":6},"o":{"a":0,"k":100,"ix":7},"sk":{"a":0,"k":0,"ix":4},"sa":{"a":0,"k":0,"ix":5},"nm":"Transformar"}],"nm":"Layer 20 Outlines - Group 115","np":1,"cix":2,"bm":0,"ix":5,"mn":"ADBE Vector Group","hd":false},{"ty":"gr","it":[{"ty":"gr","it":[{"ind":0,"ty":"sh","ix":1,"ks":{"a":0,"k":{"i":[[0.22,0],[0.101,0.057],[0,0],[0,0.22],[-0.058,0.1],[-0.306,-0.176],[0,0],[0,-0.219],[0.057,-0.101]],"o":[[-0.108,0],[0,0],[-0.204,-0.118],[-0.001,-0.108],[0.176,-0.305],[0,0],[0.204,0.117],[0,0.109],[-0.119,0.204]],"v":[[5.442,3.824],[5.124,3.74],[-5.76,-2.544],[-6.078,-3.096],[-5.993,-3.414],[-5.122,-3.648],[5.76,2.637],[6.079,3.187],[5.995,3.507]],"c":true},"ix":2},"nm":"Path 1","mn":"ADBE Vector Shape - Group","hd":false},{"ty":"fl","c":{"a":0,"k":[0.250999987125,0.063000001013,0.286000013351,1],"ix":4,"x":"var $bm_rt;\ntry {\n    $bm_rt = thisComp.layer('Controller')('Effects')('Color')('ADBE Color Control-0001');\n} catch (e) {\n    $bm_rt = value;\n}"},"o":{"a":0,"k":100,"ix":5},"r":1,"bm":0,"nm":"Fill 1","mn":"ADBE Vector Graphic - Fill","hd":false},{"ty":"tr","p":{"a":0,"k":[36.27,51.049],"ix":2},"a":{"a":0,"k":[0,0],"ix":1},"s":{"a":0,"k":[100,100],"ix":3},"r":{"a":0,"k":0,"ix":6},"o":{"a":0,"k":100,"ix":7},"sk":{"a":0,"k":0,"ix":4},"sa":{"a":0,"k":0,"ix":5},"nm":"Transformar"}],"nm":"Group 16","np":2,"cix":2,"bm":0,"ix":1,"mn":"ADBE Vector Group","hd":false},{"ty":"tr","p":{"a":0,"k":[270.099,344.222],"ix":2},"a":{"a":0,"k":[36.27,51.095],"ix":1},"s":{"a":0,"k":[500,500],"ix":3},"r":{"a":0,"k":0,"ix":6},"o":{"a":0,"k":100,"ix":7},"sk":{"a":0,"k":0,"ix":4},"sa":{"a":0,"k":0,"ix":5},"nm":"Transformar"}],"nm":"Layer 20 Outlines - Group 116","np":1,"cix":2,"bm":0,"ix":6,"mn":"ADBE Vector Group","hd":false},{"ty":"gr","it":[{"ty":"gr","it":[{"ind":0,"ty":"sh","ix":1,"ks":{"a":0,"k":{"i":[[0.22,0],[0.1,0.058],[0,0],[-0.176,0.304],[-0.305,-0.175],[0,0],[0.176,-0.306]],"o":[[-0.108,0],[0,0],[-0.304,-0.176],[0.176,-0.305],[0,0],[0.305,0.175],[-0.118,0.204]],"v":[[6.668,4.531],[6.35,4.447],[-6.987,-3.252],[-7.219,-4.122],[-6.35,-4.356],[6.986,3.344],[7.219,4.214]],"c":true},"ix":2},"nm":"Path 1","mn":"ADBE Vector Shape - Group","hd":false},{"ty":"fl","c":{"a":0,"k":[0.250999987125,0.063000001013,0.286000013351,1],"ix":4,"x":"var $bm_rt;\ntry {\n    $bm_rt = thisComp.layer('Controller')('Effects')('Color')('ADBE Color Control-0001');\n} catch (e) {\n    $bm_rt = value;\n}"},"o":{"a":0,"k":100,"ix":5},"r":1,"bm":0,"nm":"Fill 1","mn":"ADBE Vector Graphic - Fill","hd":false},{"ty":"tr","p":{"a":0,"k":[40.42,46.692],"ix":2},"a":{"a":0,"k":[0,0],"ix":1},"s":{"a":0,"k":[100,100],"ix":3},"r":{"a":0,"k":0,"ix":6},"o":{"a":0,"k":100,"ix":7},"sk":{"a":0,"k":0,"ix":4},"sa":{"a":0,"k":0,"ix":5},"nm":"Transformar"}],"nm":"Group 17","np":2,"cix":2,"bm":0,"ix":1,"mn":"ADBE Vector Group","hd":false},{"ty":"tr","p":{"a":0,"k":[290.847,322.434],"ix":2},"a":{"a":0,"k":[40.42,46.737],"ix":1},"s":{"a":0,"k":[500,500],"ix":3},"r":{"a":0,"k":0,"ix":6},"o":{"a":0,"k":100,"ix":7},"sk":{"a":0,"k":0,"ix":4},"sa":{"a":0,"k":0,"ix":5},"nm":"Transformar"}],"nm":"Layer 20 Outlines - Group 117","np":1,"cix":2,"bm":0,"ix":7,"mn":"ADBE Vector Group","hd":false},{"ty":"gr","it":[{"ty":"gr","it":[{"ind":0,"ty":"sh","ix":1,"ks":{"a":0,"k":{"i":[[1.231,0],[0.56,0.323],[0,0],[-0.176,0.305],[-0.305,-0.177],[0,0],[-0.63,1.092],[0.159,0.59],[0.528,0.304],[0,0],[0,0],[-0.175,0.304],[-0.304,-0.176],[-0.028,-0.017],[0,0],[-0.63,1.089],[1.093,0.63],[0,0.221],[-0.058,0.1],[-0.307,-0.177],[-0.632,1.091],[1.092,0.631],[0,0],[0.043,0.166],[-0.089,0.147],[-0.303,-0.175],[-0.591,0.155],[-0.307,0.529],[1.092,0.63],[0,0],[-0.175,0.305],[-0.305,-0.175],[0,0],[0.981,-1.7],[0.815,-0.278],[0.876,-1.52],[1.122,-0.095],[0.604,-1.047],[1.701,0.981],[0,0],[0.423,-0.733]],"o":[[-0.603,0],[0,0],[-0.305,-0.177],[0.176,-0.305],[0,0],[1.092,0.631],[0.305,-0.529],[-0.158,-0.59],[0,0],[0,0],[-0.304,-0.176],[0.177,-0.306],[0.03,0.018],[0,0],[1.094,0.629],[0.631,-1.092],[-0.204,-0.119],[-0.001,-0.109],[0.176,-0.305],[1.09,0.632],[0.628,-1.092],[0,0],[-0.148,-0.086],[-0.043,-0.166],[0.179,-0.298],[0.528,0.306],[0.59,-0.158],[0.63,-1.092],[0,0],[-0.304,-0.176],[0.177,-0.304],[0,0],[1.701,0.983],[-0.436,0.754],[1.305,1.089],[-0.605,1.047],[0.479,1.02],[-0.982,1.7],[0,0],[0.146,0.825],[-0.659,1.14]],"v":[[10.136,20.125],[8.362,19.649],[-23.226,1.412],[-23.459,0.541],[-22.589,0.309],[9,18.546],[12.123,17.709],[12.351,15.972],[11.287,14.586],[11.287,14.584],[11.286,14.584],[11.053,13.714],[11.923,13.48],[12.011,13.533],[14.374,14.896],[17.499,14.059],[16.661,10.935],[16.343,10.383],[16.428,10.064],[17.299,9.831],[20.424,8.994],[19.584,5.869],[17.786,4.832],[17.488,4.439],[17.559,3.952],[18.426,3.727],[20.161,3.957],[21.551,2.891],[20.712,-0.234],[-11.53,-18.847],[-11.763,-19.717],[-10.892,-19.95],[21.349,-1.338],[22.654,3.527],[20.723,5.116],[21.527,9.631],[18.739,11.398],[18.603,14.695],[13.738,15.999],[13.65,15.948],[13.226,18.346]],"c":true},"ix":2},"nm":"Path 1","mn":"ADBE Vector Shape - Group","hd":false},{"ty":"fl","c":{"a":0,"k":[0.250999987125,0.063000001013,0.286000013351,1],"ix":4,"x":"var $bm_rt;\ntry {\n    $bm_rt = thisComp.layer('Controller')('Effects')('Color')('ADBE Color Control-0001');\n} catch (e) {\n    $bm_rt = value;\n}"},"o":{"a":0,"k":100,"ix":5},"r":1,"bm":0,"nm":"Fill 1","mn":"ADBE Vector Graphic - Fill","hd":false},{"ty":"tr","p":{"a":0,"k":[30.108,40.203],"ix":2},"a":{"a":0,"k":[0,0],"ix":1},"s":{"a":0,"k":[100,100],"ix":3},"r":{"a":0,"k":0,"ix":6},"o":{"a":0,"k":100,"ix":7},"sk":{"a":0,"k":0,"ix":4},"sa":{"a":0,"k":0,"ix":5},"nm":"Transformar"}],"nm":"Group 18","np":2,"cix":2,"bm":0,"ix":1,"mn":"ADBE Vector Group","hd":false},{"ty":"tr","p":{"a":0,"k":[238.251,289.991],"ix":2},"a":{"a":0,"k":[29.901,40.248],"ix":1},"s":{"a":0,"k":[500,500],"ix":3},"r":{"a":0,"k":0,"ix":6},"o":{"a":0,"k":100,"ix":7},"sk":{"a":0,"k":0,"ix":4},"sa":{"a":0,"k":0,"ix":5},"nm":"Transformar"}],"nm":"Layer 20 Outlines - Group 118","np":1,"cix":2,"bm":0,"ix":8,"mn":"ADBE Vector Group","hd":false},{"ty":"gr","it":[{"ty":"gr","it":[{"ind":0,"ty":"sh","ix":1,"ks":{"a":0,"k":{"i":[[1.398,0.807],[0,0],[0,0],[0,0],[-0.808,1.399],[1.398,0.805],[0,0],[0,0],[-0.809,1.401],[1.399,0.808],[-0.808,1.4],[1.4,0.809],[0,0],[0,0],[-0.808,1.399]],"o":[[0,0],[0,0],[0,0],[1.398,0.808],[0.808,-1.398],[0,0],[0,0],[1.398,0.806],[0.808,-1.397],[1.399,0.808],[0.806,-1.399],[0,0],[0,0],[1.4,0.81],[0.807,-1.398]],"v":[[19.676,-1.864],[-9.859,-18.826],[-21.555,1.432],[7.327,18.018],[11.321,16.948],[10.25,12.954],[10.251,12.953],[12.702,14.368],[16.697,13.297],[15.626,9.304],[19.621,8.233],[18.549,4.239],[16.751,3.201],[16.752,3.198],[20.748,2.131]],"c":true},"ix":2},"nm":"Path 1","mn":"ADBE Vector Shape - Group","hd":false},{"ty":"fl","c":{"a":0,"k":[0.972999989986,0.913999974728,0.796000003815,1],"ix":4,"x":"var $bm_rt;\ntry {\n    $bm_rt = thisComp.layer('Controller').effect('Color 8')('ADBE Color Control-0001');\n} catch (e) {\n    $bm_rt = value;\n}"},"o":{"a":0,"k":100,"ix":5},"r":1,"bm":0,"nm":"Fill 1","mn":"ADBE Vector Graphic - Fill","hd":false},{"ty":"tr","p":{"a":0,"k":[28.756,39.631],"ix":2},"a":{"a":0,"k":[0,0],"ix":1},"s":{"a":0,"k":[100,100],"ix":3},"r":{"a":0,"k":0,"ix":6},"o":{"a":0,"k":100,"ix":7},"sk":{"a":0,"k":0,"ix":4},"sa":{"a":0,"k":0,"ix":5},"nm":"Transformar"}],"nm":"Group 19","np":2,"cix":2,"bm":0,"ix":1,"mn":"ADBE Vector Group","hd":false},{"ty":"tr","p":{"a":0,"k":[231.489,285.865],"ix":2},"a":{"a":0,"k":[28.548,39.423],"ix":1},"s":{"a":0,"k":[500,500],"ix":3},"r":{"a":0,"k":0,"ix":6},"o":{"a":0,"k":100,"ix":7},"sk":{"a":0,"k":0,"ix":4},"sa":{"a":0,"k":0,"ix":5},"nm":"Transformar"}],"nm":"Layer 20 Outlines - Group 119","np":1,"cix":2,"bm":0,"ix":9,"mn":"ADBE Vector Group","hd":false},{"ty":"gr","it":[{"ty":"gr","it":[{"ind":0,"ty":"sh","ix":1,"ks":{"a":0,"k":{"i":[[1.398,0.807],[0,0],[0,0],[0,0],[-0.808,1.399],[1.397,0.805],[0,0],[0,0],[-0.809,1.4],[1.4,0.809],[-0.809,1.4],[1.4,0.809],[0,0],[0,0],[-0.809,1.399]],"o":[[0,0],[0,0],[0,0],[1.399,0.806],[0.808,-1.398],[0,0],[0,0],[1.398,0.806],[0.807,-1.398],[1.4,0.809],[0.806,-1.4],[0,0],[0,0],[1.399,0.81],[0.806,-1.397]],"v":[[21.03,-1.038],[-11.212,-19.651],[-22.908,0.607],[8.68,18.845],[12.674,17.774],[11.604,13.78],[11.605,13.779],[14.055,15.194],[18.051,14.124],[16.979,10.13],[20.975,9.06],[19.902,5.065],[18.104,4.026],[18.106,4.024],[22.102,2.956]],"c":true},"ix":2},"nm":"Path 1","mn":"ADBE Vector Shape - Group","hd":false},{"ty":"fl","c":{"a":0,"k":[1,1,1,1],"ix":4,"x":"var $bm_rt;\ntry {\n    $bm_rt = thisComp.layer('Controller')('Effects')('Color 5')('ADBE Color Control-0001');\n} catch (e) {\n    $bm_rt = value;\n}"},"o":{"a":0,"k":100,"ix":5},"r":1,"bm":0,"nm":"Fill 1","mn":"ADBE Vector Graphic - Fill","hd":false},{"ty":"tr","p":{"a":0,"k":[30.108,40.456],"ix":2},"a":{"a":0,"k":[0,0],"ix":1},"s":{"a":0,"k":[100,100],"ix":3},"r":{"a":0,"k":0,"ix":6},"o":{"a":0,"k":100,"ix":7},"sk":{"a":0,"k":0,"ix":4},"sa":{"a":0,"k":0,"ix":5},"nm":"Transformar"}],"nm":"Group 20","np":2,"cix":2,"bm":0,"ix":1,"mn":"ADBE Vector Group","hd":false},{"ty":"tr","p":{"a":0,"k":[238.253,289.994],"ix":2},"a":{"a":0,"k":[29.901,40.249],"ix":1},"s":{"a":0,"k":[500,500],"ix":3},"r":{"a":0,"k":0,"ix":6},"o":{"a":0,"k":100,"ix":7},"sk":{"a":0,"k":0,"ix":4},"sa":{"a":0,"k":0,"ix":5},"nm":"Transformar"}],"nm":"Layer 20 Outlines - Group 220","np":1,"cix":2,"bm":0,"ix":10,"mn":"ADBE Vector Group","hd":false}],"ip":0,"op":150.000006109625,"st":0,"ct":1,"bm":0},{"ddd":0,"ind":8,"ty":4,"nm":"Layer 20 Outlines - Group 26 :M 3","parent":10,"td":1,"sr":1,"ks":{"o":{"a":0,"k":100,"ix":11},"r":{"a":0,"k":0,"ix":10},"p":{"a":0,"k":[250.001,264.708,0],"ix":2,"l":2},"a":{"a":0,"k":[250.001,264.708,0],"ix":1,"l":2},"s":{"a":0,"k":[100,100,100],"ix":6,"l":2}},"ao":0,"shapes":[{"ty":"gr","it":[{"ty":"gr","it":[{"ind":0,"ty":"sh","ix":1,"ks":{"a":0,"k":{"i":[[4.418,0],[0,0],[0,4.418],[0,0],[-4.419,0],[0,0],[0,-4.418],[0,0]],"o":[[0,0],[-4.419,0],[0,0],[0,-4.418],[0,0],[4.418,0],[0,0],[0,4.418]],"v":[[23.363,28.422],[-23.363,28.422],[-31.363,20.422],[-31.363,-20.422],[-23.363,-28.422],[23.363,-28.422],[31.363,-20.422],[31.363,20.422]],"c":true},"ix":2},"nm":"Path 1","mn":"ADBE Vector Shape - Group","hd":false},{"ty":"fl","c":{"a":0,"k":[1,1,1,1],"ix":4,"x":"var $bm_rt;\ntry {\n    $bm_rt = thisComp.layer('Controller')('Effects')('Color 5')('ADBE Color Control-0001');\n} catch (e) {\n    $bm_rt = value;\n}"},"o":{"a":0,"k":100,"ix":5},"r":1,"bm":0,"nm":"Fill 1","mn":"ADBE Vector Graphic - Fill","hd":false},{"ty":"tr","p":{"a":0,"k":[32.251,35.192],"ix":2},"a":{"a":0,"k":[0,0],"ix":1},"s":{"a":0,"k":[100,100],"ix":3},"r":{"a":0,"k":0,"ix":6},"o":{"a":0,"k":100,"ix":7},"sk":{"a":0,"k":0,"ix":4},"sa":{"a":0,"k":0,"ix":5},"nm":"Transformar"}],"nm":"Group 31","np":2,"cix":2,"bm":0,"ix":1,"mn":"ADBE Vector Group","hd":false},{"ty":"tr","p":{"a":0,"k":[250.001,264.707],"ix":2},"a":{"a":0,"k":[32.251,35.192],"ix":1},"s":{"a":0,"k":[500,500],"ix":3},"r":{"a":0,"k":0,"ix":6},"o":{"a":0,"k":100,"ix":7},"sk":{"a":0,"k":0,"ix":4},"sa":{"a":0,"k":0,"ix":5},"nm":"Transformar"}],"nm":"Layer 20 Outlines - Group 331","np":1,"cix":2,"bm":0,"ix":1,"mn":"ADBE Vector Group","hd":false}],"ip":0,"op":150.000006109625,"st":0,"ct":1,"bm":0},{"ddd":0,"ind":9,"ty":4,"nm":"Layer 20 Outlines - Group 5 :M","parent":10,"tt":1,"tp":8,"sr":1,"ks":{"o":{"a":0,"k":100,"ix":11},"r":{"a":1,"k":[{"i":{"x":[0.63],"y":[1]},"o":{"x":[0.37],"y":[0]},"t":5,"s":[0]},{"i":{"x":[0.63],"y":[1]},"o":{"x":[0.37],"y":[0]},"t":20,"s":[8]},{"i":{"x":[0.63],"y":[1]},"o":{"x":[0.37],"y":[0]},"t":35,"s":[-6]},{"i":{"x":[0.833],"y":[1]},"o":{"x":[0.167],"y":[0]},"t":50,"s":[0]},{"i":{"x":[0.63],"y":[1]},"o":{"x":[0.37],"y":[0]},"t":80,"s":[0]},{"i":{"x":[0.63],"y":[1]},"o":{"x":[0.37],"y":[0]},"t":95,"s":[8]},{"i":{"x":[0.63],"y":[1]},"o":{"x":[0.37],"y":[0]},"t":110,"s":[-6]},{"t":125.000005091354,"s":[0]}],"ix":10},"p":{"a":1,"k":[{"i":{"x":0.63,"y":1},"o":{"x":0.37,"y":0},"t":0,"s":[385.197,207.649,0],"to":[3.31,-0.709,0],"ti":[0,0,0]},{"i":{"x":0.63,"y":1},"o":{"x":0.37,"y":0},"t":15,"s":[405.056,203.394,0],"to":[0,0,0],"ti":[0,0,0]},{"i":{"x":0.63,"y":1},"o":{"x":0.37,"y":0},"t":30,"s":[379.5,203.394,0],"to":[0,0,0],"ti":[-0.95,-0.709,0]},{"i":{"x":0.833,"y":0.833},"o":{"x":0.167,"y":0.167},"t":45,"s":[385.197,207.649,0],"to":[0,0,0],"ti":[0,0,0]},{"i":{"x":0.63,"y":1},"o":{"x":0.37,"y":0},"t":75,"s":[385.197,207.649,0],"to":[3.31,-0.709,0],"ti":[0,0,0]},{"i":{"x":0.63,"y":1},"o":{"x":0.37,"y":0},"t":90,"s":[405.056,203.394,0],"to":[0,0,0],"ti":[0,0,0]},{"i":{"x":0.63,"y":1},"o":{"x":0.37,"y":0},"t":105,"s":[379.5,203.394,0],"to":[0,0,0],"ti":[-0.95,-0.709,0]},{"t":120.0000048877,"s":[385.197,207.649,0]}],"ix":2,"l":2},"a":{"a":0,"k":[385.197,207.649,0],"ix":1,"l":2},"s":{"a":0,"k":[100,100,100],"ix":6,"l":2}},"ao":0,"shapes":[{"ty":"gr","it":[{"ty":"gr","it":[{"ind":0,"ty":"sh","ix":1,"ks":{"a":0,"k":{"i":[[0.338,0.586],[0.586,-0.338],[-0.338,-0.586],[-0.586,0.339]],"o":[[-0.338,-0.586],[-0.586,0.339],[0.339,0.586],[0.586,-0.339]],"v":[[1.061,-0.613],[-0.612,-1.061],[-1.061,0.612],[0.613,1.06]],"c":true},"ix":2},"nm":"Path 1","mn":"ADBE Vector Shape - Group","hd":false},{"ty":"fl","c":{"a":0,"k":[0.250999987125,0.063000001013,0.286000013351,1],"ix":4,"x":"var $bm_rt;\ntry {\n    $bm_rt = thisComp.layer('Controller')('Effects')('Color')('ADBE Color Control-0001');\n} catch (e) {\n    $bm_rt = value;\n}"},"o":{"a":0,"k":100,"ix":5},"r":1,"bm":0,"nm":"Fill 1","mn":"ADBE Vector Graphic - Fill","hd":false},{"ty":"tr","p":{"a":0,"k":[59.955,34.519],"ix":2},"a":{"a":0,"k":[0,0],"ix":1},"s":{"a":0,"k":[100,100],"ix":3},"r":{"a":0,"k":0,"ix":6},"o":{"a":0,"k":100,"ix":7},"sk":{"a":0,"k":0,"ix":4},"sa":{"a":0,"k":0,"ix":5},"nm":"Transformar"}],"nm":"Group 5","np":2,"cix":2,"bm":0,"ix":1,"mn":"ADBE Vector Group","hd":false},{"ty":"tr","p":{"a":0,"k":[388.523,261.344],"ix":2},"a":{"a":0,"k":[59.955,34.519],"ix":1},"s":{"a":0,"k":[500,500],"ix":3},"r":{"a":0,"k":0,"ix":6},"o":{"a":0,"k":100,"ix":7},"sk":{"a":0,"k":0,"ix":4},"sa":{"a":0,"k":0,"ix":5},"nm":"Transformar"}],"nm":"Layer 20 Outlines - Group 5","np":1,"cix":2,"bm":0,"ix":1,"mn":"ADBE Vector Group","hd":false},{"ty":"gr","it":[{"ty":"gr","it":[{"ind":0,"ty":"sh","ix":1,"ks":{"a":0,"k":{"i":[[0,0],[0,0],[0,0],[0,0],[1.467,1.361]],"o":[[0,0],[0,0],[0,0],[0,-2.015],[0,0]],"v":[[-8.56,-6.761],[4.245,15.418],[12.915,10.379],[12.915,-12.586],[10.615,-17.863]],"c":true},"ix":2},"nm":"Path 1","mn":"ADBE Vector Shape - Group","hd":false},{"ind":1,"ty":"sh","ix":2,"ks":{"a":0,"k":{"i":[[0.111,0],[0.054,0.014],[0.084,0.147],[0,0],[-0.043,0.162],[-0.146,0.084],[0,0],[-0.206,-0.169],[0,-2.545],[0,0],[0.196,-0.113],[0,0]],"o":[[-0.055,0],[-0.163,-0.045],[0,0],[-0.084,-0.147],[0.045,-0.165],[0,0],[0.229,-0.131],[1.965,1.618],[0,0],[0,0.227],[0,0],[-0.098,0.056]],"v":[[4.012,16.926],[3.847,16.904],[3.461,16.607],[-9.982,-6.675],[-10.046,-7.158],[-9.749,-7.545],[10.372,-19.195],[11.096,-19.135],[14.189,-12.586],[14.189,10.748],[13.871,11.299],[4.331,16.84]],"c":true},"ix":2},"nm":"Path 2","mn":"ADBE Vector Shape - Group","hd":false},{"ty":"mm","mm":1,"nm":"Merge Paths 1","mn":"ADBE Vector Filter - Merge","hd":false},{"ty":"fl","c":{"a":0,"k":[0.250999987125,0.063000001013,0.286000013351,1],"ix":4,"x":"var $bm_rt;\ntry {\n    $bm_rt = thisComp.layer('Controller')('Effects')('Color')('ADBE Color Control-0001');\n} catch (e) {\n    $bm_rt = value;\n}"},"o":{"a":0,"k":100,"ix":5},"r":1,"bm":0,"nm":"Fill 1","mn":"ADBE Vector Graphic - Fill","hd":false},{"ty":"tr","p":{"a":0,"k":[54.161,24.797],"ix":2},"a":{"a":0,"k":[0,0],"ix":1},"s":{"a":0,"k":[100,100],"ix":3},"r":{"a":0,"k":0,"ix":6},"o":{"a":0,"k":100,"ix":7},"sk":{"a":0,"k":0,"ix":4},"sa":{"a":0,"k":0,"ix":5},"nm":"Transformar"}],"nm":"Group 6","np":4,"cix":2,"bm":0,"ix":1,"mn":"ADBE Vector Group","hd":false},{"ty":"tr","p":{"a":0,"k":[359.61,212.852],"ix":2},"a":{"a":0,"k":[54.172,24.821],"ix":1},"s":{"a":0,"k":[500,500],"ix":3},"r":{"a":0,"k":0,"ix":6},"o":{"a":0,"k":100,"ix":7},"sk":{"a":0,"k":0,"ix":4},"sa":{"a":0,"k":0,"ix":5},"nm":"Transformar"}],"nm":"Layer 20 Outlines - Group 6","np":1,"cix":2,"bm":0,"ix":2,"mn":"ADBE Vector Group","hd":false},{"ty":"gr","it":[{"ty":"gr","it":[{"ind":0,"ty":"sh","ix":1,"ks":{"a":0,"k":{"i":[[0,0],[0,0],[0,0],[0,0]],"o":[[0,0],[0,0],[0,0],[0,0]],"v":[[-0.805,-14.176],[-9.441,-9.307],[4.001,13.975],[13.252,8.693]],"c":true},"ix":2},"nm":"Path 1","mn":"ADBE Vector Shape - Group","hd":false},{"ty":"fl","c":{"a":0,"k":[0.882000029087,0.446999996901,0.446999996901,1],"ix":4,"x":"var $bm_rt;\ntry {\n    $bm_rt = thisComp.layer('Controller').effect('Color 9')('ADBE Color Control-0001');\n} catch (e) {\n    $bm_rt = value;\n}"},"o":{"a":0,"k":100,"ix":5},"r":1,"bm":0,"nm":"Fill 1","mn":"ADBE Vector Graphic - Fill","hd":false},{"ty":"tr","p":{"a":0,"k":[54.172,27.111],"ix":2},"a":{"a":0,"k":[0,0],"ix":1},"s":{"a":0,"k":[100,100],"ix":3},"r":{"a":0,"k":0,"ix":6},"o":{"a":0,"k":100,"ix":7},"sk":{"a":0,"k":0,"ix":4},"sa":{"a":0,"k":0,"ix":5},"nm":"Transformar"}],"nm":"Group 9","np":2,"cix":2,"bm":0,"ix":1,"mn":"ADBE Vector Group","hd":false},{"ty":"tr","p":{"a":0,"k":[359.609,224.302],"ix":2},"a":{"a":0,"k":[54.172,27.111],"ix":1},"s":{"a":0,"k":[500,500],"ix":3},"r":{"a":0,"k":0,"ix":6},"o":{"a":0,"k":100,"ix":7},"sk":{"a":0,"k":0,"ix":4},"sa":{"a":0,"k":0,"ix":5},"nm":"Transformar"}],"nm":"Layer 20 Outlines - Group 9","np":1,"cix":2,"bm":0,"ix":3,"mn":"ADBE Vector Group","hd":false},{"ty":"gr","it":[{"ty":"gr","it":[{"ind":0,"ty":"sh","ix":1,"ks":{"a":0,"k":{"i":[[0,0],[1.748,1.438],[0,0],[0,0]],"o":[[0,-2.439],[0,0],[0,0],[0,0]],"v":[[9.398,-7.983],[6.536,-14.04],[-4.967,-7.204],[9.192,15.834]],"c":true},"ix":2},"nm":"Path 1","mn":"ADBE Vector Shape - Group","hd":false},{"ty":"fl","c":{"a":0,"k":[0.773000001907,0.266999989748,0.266999989748,1],"ix":4,"x":"var $bm_rt;\ntry {\n    $bm_rt = thisComp.layer('Controller').effect('Color 10')('ADBE Color Control-0001');\n} catch (e) {\n    $bm_rt = value;\n}"},"o":{"a":0,"k":100,"ix":5},"r":1,"bm":0,"nm":"Fill 1","mn":"ADBE Vector Graphic - Fill","hd":false},{"ty":"tr","p":{"a":0,"k":[58.216,20.195],"ix":2},"a":{"a":0,"k":[0,0],"ix":1},"s":{"a":0,"k":[100,100],"ix":3},"r":{"a":0,"k":0,"ix":6},"o":{"a":0,"k":100,"ix":7},"sk":{"a":0,"k":0,"ix":4},"sa":{"a":0,"k":0,"ix":5},"nm":"Transformar"}],"nm":"Group 10","np":2,"cix":2,"bm":0,"ix":1,"mn":"ADBE Vector Group","hd":false},{"ty":"tr","p":{"a":0,"k":[379.826,189.722],"ix":2},"a":{"a":0,"k":[58.216,20.195],"ix":1},"s":{"a":0,"k":[500,500],"ix":3},"r":{"a":0,"k":0,"ix":6},"o":{"a":0,"k":100,"ix":7},"sk":{"a":0,"k":0,"ix":4},"sa":{"a":0,"k":0,"ix":5},"nm":"Transformar"}],"nm":"Layer 20 Outlines - Group 110","np":1,"cix":2,"bm":0,"ix":4,"mn":"ADBE Vector Group","hd":false},{"ty":"gr","it":[{"ty":"gr","it":[{"ind":0,"ty":"sh","ix":1,"ks":{"a":0,"k":{"i":[[0.108,0],[0.117,0.204],[-0.305,0.175],[0,0],[-0.175,-0.304],[0.305,-0.176],[0,0]],"o":[[-0.22,0],[-0.176,-0.306],[0,0],[0.305,-0.176],[0.176,0.305],[0,0],[-0.1,0.059]],"v":[[-1.173,1.358],[-1.725,1.04],[-1.492,0.169],[0.854,-1.182],[1.725,-0.949],[1.492,-0.078],[-0.855,1.272]],"c":true},"ix":2},"nm":"Path 1","mn":"ADBE Vector Shape - Group","hd":false},{"ty":"fl","c":{"a":0,"k":[0.250999987125,0.063000001013,0.286000013351,1],"ix":4,"x":"var $bm_rt;\ntry {\n    $bm_rt = thisComp.layer('Controller')('Effects')('Color')('ADBE Color Control-0001');\n} catch (e) {\n    $bm_rt = value;\n}"},"o":{"a":0,"k":100,"ix":5},"r":1,"bm":0,"nm":"Fill 1","mn":"ADBE Vector Graphic - Fill","hd":false},{"ty":"tr","p":{"a":0,"k":[18.094,48.661],"ix":2},"a":{"a":0,"k":[0,0],"ix":1},"s":{"a":0,"k":[100,100],"ix":3},"r":{"a":0,"k":0,"ix":6},"o":{"a":0,"k":100,"ix":7},"sk":{"a":0,"k":0,"ix":4},"sa":{"a":0,"k":0,"ix":5},"nm":"Transformar"}],"nm":"Group 21","np":2,"cix":2,"bm":0,"ix":1,"mn":"ADBE Vector Group","hd":false},{"ty":"tr","p":{"a":0,"k":[179.219,332.282],"ix":2},"a":{"a":0,"k":[18.094,48.707],"ix":1},"s":{"a":0,"k":[500,500],"ix":3},"r":{"a":0,"k":0,"ix":6},"o":{"a":0,"k":100,"ix":7},"sk":{"a":0,"k":0,"ix":4},"sa":{"a":0,"k":0,"ix":5},"nm":"Transformar"}],"nm":"Layer 20 Outlines - Group 221","np":1,"cix":2,"bm":0,"ix":5,"mn":"ADBE Vector Group","hd":false},{"ty":"gr","it":[{"ty":"gr","it":[{"ind":0,"ty":"sh","ix":1,"ks":{"a":0,"k":{"i":[[0.108,0],[0.118,0.205],[-0.305,0.176],[0,0],[-0.177,-0.304],[0.304,-0.176],[0,0]],"o":[[-0.22,0],[-0.176,-0.305],[0,0],[0.306,-0.175],[0.176,0.305],[0,0],[-0.1,0.058]],"v":[[-2.633,2.202],[-3.185,1.884],[-2.952,1.014],[2.314,-2.027],[3.184,-1.794],[2.952,-0.923],[-2.314,2.117]],"c":true},"ix":2},"nm":"Path 1","mn":"ADBE Vector Shape - Group","hd":false},{"ty":"fl","c":{"a":0,"k":[0.250999987125,0.063000001013,0.286000013351,1],"ix":4,"x":"var $bm_rt;\ntry {\n    $bm_rt = thisComp.layer('Controller')('Effects')('Color')('ADBE Color Control-0001');\n} catch (e) {\n    $bm_rt = value;\n}"},"o":{"a":0,"k":100,"ix":5},"r":1,"bm":0,"nm":"Fill 1","mn":"ADBE Vector Graphic - Fill","hd":false},{"ty":"tr","p":{"a":0,"k":[22.478,52.878],"ix":2},"a":{"a":0,"k":[0,0],"ix":1},"s":{"a":0,"k":[100,100],"ix":3},"r":{"a":0,"k":0,"ix":6},"o":{"a":0,"k":100,"ix":7},"sk":{"a":0,"k":0,"ix":4},"sa":{"a":0,"k":0,"ix":5},"nm":"Transformar"}],"nm":"Group 22","np":2,"cix":2,"bm":0,"ix":1,"mn":"ADBE Vector Group","hd":false},{"ty":"tr","p":{"a":0,"k":[201.137,353.366],"ix":2},"a":{"a":0,"k":[22.478,52.923],"ix":1},"s":{"a":0,"k":[500,500],"ix":3},"r":{"a":0,"k":0,"ix":6},"o":{"a":0,"k":100,"ix":7},"sk":{"a":0,"k":0,"ix":4},"sa":{"a":0,"k":0,"ix":5},"nm":"Transformar"}],"nm":"Layer 20 Outlines - Group 222","np":1,"cix":2,"bm":0,"ix":6,"mn":"ADBE Vector Group","hd":false},{"ty":"gr","it":[{"ty":"gr","it":[{"ind":0,"ty":"sh","ix":1,"ks":{"a":0,"k":{"i":[[0,0],[-0.631,-1.091],[-1.094,0.631],[0,0],[0,0],[0,0],[0.159,-0.589],[-0.305,-0.528],[-1.093,0.623],[-0.176,-0.305],[0.304,-0.176],[0,0],[0,0],[0.158,-0.59],[-0.306,-0.529],[-1.097,0.631],[-0.177,-0.305],[0,-0.108],[0.205,-0.118],[0.159,-0.59],[-0.305,-0.53],[-0.59,-0.157],[-0.53,0.305],[0,0],[-0.175,-0.306],[0.305,-0.176]],"o":[[-1.09,0.633],[0.629,1.093],[0,0],[0,0],[0,0],[-0.53,0.306],[-0.157,0.591],[0.628,1.09],[0.305,-0.176],[0.175,0.305],[0,0],[0,0],[-0.529,0.305],[-0.159,0.592],[0.629,1.091],[0.302,-0.175],[0.057,0.1],[0.001,0.221],[-0.53,0.304],[-0.158,0.59],[0.306,0.528],[0.587,0.157],[0,0],[0.304,-0.175],[0.176,0.304],[0,0]],"v":[[-12.671,14.881],[-13.505,18.006],[-10.379,18.843],[21.802,0.265],[10.742,-18.893],[-20.787,-0.691],[-21.854,0.699],[-21.625,2.433],[-18.504,3.274],[-17.635,3.508],[-17.869,4.377],[-17.871,4.38],[-20.315,5.79],[-21.38,7.179],[-21.151,8.916],[-18.025,9.752],[-17.155,9.986],[-17.071,10.304],[-17.39,10.856],[-18.457,12.244],[-18.228,13.981],[-16.839,15.045],[-15.103,14.814],[-13.307,13.778],[-12.437,14.011],[-12.67,14.881]],"c":true},"ix":2},"nm":"Path 1","mn":"ADBE Vector Shape - Group","hd":false},{"ind":1,"ty":"sh","ix":2,"ks":{"a":0,"k":{"i":[[0.604,0],[0.658,1.14],[-0.161,0.815],[0.721,0.192],[0.475,0.825],[-0.247,0.919],[-0.089,0.19],[0.604,1.046],[-0.247,0.921],[-0.824,0.474],[0,0],[0.434,0.752],[-0.247,0.919],[-0.824,0.477],[0,0],[-0.165,-0.044],[-0.085,-0.146],[0,0],[0.044,-0.164],[0.146,-0.086],[0,0]],"o":[[-1.233,0],[-0.448,-0.776],[-0.685,0.255],[-0.919,-0.246],[-0.476,-0.824],[0.055,-0.207],[-1.122,-0.095],[-0.477,-0.824],[0.246,-0.92],[0,0],[-0.762,-0.275],[-0.476,-0.822],[0.246,-0.92],[0,0],[0.147,-0.085],[0.163,0.044],[0,0],[0.084,0.146],[-0.043,0.162],[0,0],[-0.559,0.324]],"v":[[-11.519,20.423],[-14.609,18.644],[-15.018,16.178],[-17.169,16.275],[-19.331,14.618],[-19.687,11.915],[-19.47,11.318],[-22.254,9.554],[-22.611,6.85],[-20.951,4.687],[-20.861,4.633],[-22.728,3.071],[-23.084,0.369],[-21.425,-1.795],[10.656,-20.314],[11.14,-20.378],[11.527,-20.081],[23.224,0.179],[23.287,0.662],[22.991,1.05],[-9.743,19.946]],"c":true},"ix":2},"nm":"Path 2","mn":"ADBE Vector Shape - Group","hd":false},{"ty":"mm","mm":1,"nm":"Merge Paths 1","mn":"ADBE Vector Filter - Merge","hd":false},{"ty":"fl","c":{"a":0,"k":[0.250999987125,0.063000001013,0.286000013351,1],"ix":4,"x":"var $bm_rt;\ntry {\n    $bm_rt = thisComp.layer('Controller')('Effects')('Color')('ADBE Color Control-0001');\n} catch (e) {\n    $bm_rt = value;\n}"},"o":{"a":0,"k":100,"ix":5},"r":1,"bm":0,"nm":"Fill 1","mn":"ADBE Vector Graphic - Fill","hd":false},{"ty":"tr","p":{"a":0,"k":[34.629,39.078],"ix":2},"a":{"a":0,"k":[0,0],"ix":1},"s":{"a":0,"k":[100,100],"ix":3},"r":{"a":0,"k":0,"ix":6},"o":{"a":0,"k":100,"ix":7},"sk":{"a":0,"k":0,"ix":4},"sa":{"a":0,"k":0,"ix":5},"nm":"Transformar"}],"nm":"Group 23","np":4,"cix":2,"bm":0,"ix":1,"mn":"ADBE Vector Group","hd":false},{"ty":"tr","p":{"a":0,"k":[262.146,284.193],"ix":2},"a":{"a":0,"k":[34.68,39.089],"ix":1},"s":{"a":0,"k":[500,500],"ix":3},"r":{"a":0,"k":0,"ix":6},"o":{"a":0,"k":100,"ix":7},"sk":{"a":0,"k":0,"ix":4},"sa":{"a":0,"k":0,"ix":5},"nm":"Transformar"}],"nm":"Layer 20 Outlines - Group 223","np":1,"cix":2,"bm":0,"ix":7,"mn":"ADBE Vector Group","hd":false},{"ty":"gr","it":[{"ty":"gr","it":[{"ind":0,"ty":"sh","ix":1,"ks":{"a":0,"k":{"i":[[0,0],[0,0],[-0.809,-1.398],[-1.398,0.801],[0,0],[-0.809,-1.399],[-1.4,0.806],[-0.81,-1.4],[-1.401,0.81],[0,0],[-0.807,-1.396],[-1.4,0.807],[0,0]],"o":[[0,0],[-1.399,0.808],[0.805,1.396],[0,0],[-1.399,0.808],[0.806,1.397],[-1.4,0.806],[0.806,1.396],[0,0],[-1.397,0.81],[0.808,1.4],[0,0],[0,0]],"v":[[9.62,-18.999],[-19.439,-2.444],[-20.509,1.55],[-16.521,2.624],[-18.966,4.034],[-20.036,8.033],[-16.042,9.103],[-17.112,13.097],[-13.117,14.163],[-11.322,13.127],[-12.391,17.122],[-8.395,18.192],[21.318,1.261]],"c":true},"ix":2},"nm":"Path 1","mn":"ADBE Vector Shape - Group","hd":false},{"ty":"fl","c":{"a":0,"k":[0.776000022888,0.600000023842,0.458999991417,1],"ix":4,"x":"var $bm_rt;\ntry {\n    $bm_rt = thisComp.layer('Controller')('Effects')('Color 4')('ADBE Color Control-0001');\n} catch (e) {\n    $bm_rt = value;\n}"},"o":{"a":0,"k":100,"ix":5},"r":1,"bm":0,"nm":"Fill 1","mn":"ADBE Vector Graphic - Fill","hd":false},{"ty":"tr","p":{"a":0,"k":[35.983,38.314],"ix":2},"a":{"a":0,"k":[0,0],"ix":1},"s":{"a":0,"k":[100,100],"ix":3},"r":{"a":0,"k":0,"ix":6},"o":{"a":0,"k":100,"ix":7},"sk":{"a":0,"k":0,"ix":4},"sa":{"a":0,"k":0,"ix":5},"nm":"Transformar"}],"nm":"Group 24","np":2,"cix":2,"bm":0,"ix":1,"mn":"ADBE Vector Group","hd":false},{"ty":"tr","p":{"a":0,"k":[269.704,279.281],"ix":2},"a":{"a":0,"k":[36.191,38.106],"ix":1},"s":{"a":0,"k":[500,500],"ix":3},"r":{"a":0,"k":0,"ix":6},"o":{"a":0,"k":100,"ix":7},"sk":{"a":0,"k":0,"ix":4},"sa":{"a":0,"k":0,"ix":5},"nm":"Transformar"}],"nm":"Layer 20 Outlines - Group 224","np":1,"cix":2,"bm":0,"ix":8,"mn":"ADBE Vector Group","hd":false},{"ty":"gr","it":[{"ty":"gr","it":[{"ind":0,"ty":"sh","ix":1,"ks":{"a":0,"k":{"i":[[0,0],[0,0],[-0.808,-1.398],[-1.398,0.801],[0,0],[-0.81,-1.399],[-1.4,0.808],[-0.809,-1.4],[-1.401,0.809],[0,0],[-0.807,-1.397],[-1.4,0.807],[0,0]],"o":[[0,0],[-1.398,0.808],[0.806,1.396],[0,0],[-1.399,0.808],[0.806,1.397],[-1.4,0.808],[0.806,1.396],[0,0],[-1.397,0.809],[0.807,1.398],[0,0],[0,0]],"v":[[11.131,-19.983],[-20.951,-1.461],[-22.021,2.534],[-18.032,3.608],[-20.477,5.017],[-21.546,9.016],[-17.553,10.085],[-18.622,14.081],[-14.628,15.147],[-12.833,14.111],[-13.902,18.105],[-9.906,19.176],[22.829,0.277]],"c":true},"ix":2},"nm":"Path 1","mn":"ADBE Vector Shape - Group","hd":false},{"ty":"fl","c":{"a":0,"k":[0.634999990463,0.430999994278,0.340999990702,1],"ix":4,"x":"var $bm_rt;\ntry {\n    $bm_rt = thisComp.layer('Controller').effect('Color 11')('ADBE Color Control-0001');\n} catch (e) {\n    $bm_rt = value;\n}"},"o":{"a":0,"k":100,"ix":5},"r":1,"bm":0,"nm":"Fill 1","mn":"ADBE Vector Graphic - Fill","hd":false},{"ty":"tr","p":{"a":0,"k":[34.473,39.297],"ix":2},"a":{"a":0,"k":[0,0],"ix":1},"s":{"a":0,"k":[100,100],"ix":3},"r":{"a":0,"k":0,"ix":6},"o":{"a":0,"k":100,"ix":7},"sk":{"a":0,"k":0,"ix":4},"sa":{"a":0,"k":0,"ix":5},"nm":"Transformar"}],"nm":"Group 25","np":2,"cix":2,"bm":0,"ix":1,"mn":"ADBE Vector Group","hd":false},{"ty":"tr","p":{"a":0,"k":[262.151,284.198],"ix":2},"a":{"a":0,"k":[34.681,39.09],"ix":1},"s":{"a":0,"k":[500,500],"ix":3},"r":{"a":0,"k":0,"ix":6},"o":{"a":0,"k":100,"ix":7},"sk":{"a":0,"k":0,"ix":4},"sa":{"a":0,"k":0,"ix":5},"nm":"Transformar"}],"nm":"Layer 20 Outlines - Group 225","np":1,"cix":2,"bm":0,"ix":9,"mn":"ADBE Vector Group","hd":false}],"ip":0,"op":150.000006109625,"st":0,"ct":1,"bm":0},{"ddd":0,"ind":10,"ty":4,"nm":"Layer 20 Outlines - Group 26 :M","sr":1,"ks":{"o":{"a":0,"k":100,"ix":11},"r":{"a":0,"k":0,"ix":10},"p":{"a":0,"k":[250.001,264.708,0],"ix":2,"l":2},"a":{"a":0,"k":[250.001,264.708,0],"ix":1,"l":2},"s":{"a":1,"k":[{"i":{"x":[0.63,0.63,0.63],"y":[1,1,1]},"o":{"x":[0.37,0.37,0.37],"y":[0,0,0]},"t":0,"s":[100,100,100]},{"i":{"x":[0.63,0.63,0.63],"y":[1,1,1]},"o":{"x":[0.37,0.37,0.37],"y":[0,0,0]},"t":15,"s":[125,125,100]},{"i":{"x":[0.63,0.63,0.63],"y":[1,1,1]},"o":{"x":[0.37,0.37,0.37],"y":[0,0,0]},"t":30,"s":[90,90,100]},{"i":{"x":[0.63,0.63,0.63],"y":[1,1,1]},"o":{"x":[0.37,0.37,0.37],"y":[0,0,0]},"t":45,"s":[100,100,100]},{"i":{"x":[0.63,0.63,0.63],"y":[1,1,1]},"o":{"x":[0.37,0.37,0.37],"y":[0,0,0]},"t":75,"s":[100,100,100]},{"i":{"x":[0.63,0.63,0.63],"y":[1,1,1]},"o":{"x":[0.37,0.37,0.37],"y":[0,0,0]},"t":90,"s":[125,125,100]},{"i":{"x":[0.63,0.63,0.63],"y":[1,1,1]},"o":{"x":[0.37,0.37,0.37],"y":[0,0,0]},"t":105,"s":[90,90,100]},{"t":120.0000048877,"s":[100,100,100]}],"ix":6,"l":2}},"ao":0,"shapes":[{"ty":"gr","it":[{"ty":"gr","it":[{"ind":0,"ty":"sh","ix":1,"ks":{"a":0,"k":{"i":[[0.352,0],[0,0.352],[0,0],[3.972,0],[0,0],[0,0.352],[-0.352,0],[0,0],[0,-4.675],[0,0]],"o":[[-0.352,0],[0,0],[0,-3.971],[0,0],[-0.352,0],[0,-0.351],[0,0],[4.674,0],[0,0],[0,0.352]],"v":[[21.072,19.826],[20.435,19.189],[20.435,-11.349],[13.231,-18.553],[-21.072,-18.553],[-21.709,-19.19],[-21.072,-19.826],[13.231,-19.826],[21.709,-11.349],[21.709,19.189]],"c":true},"ix":2},"nm":"Path 1","mn":"ADBE Vector Shape - Group","hd":false},{"ty":"fl","c":{"a":0,"k":[0.250999987125,0.063000001013,0.286000013351,1],"ix":4,"x":"var $bm_rt;\ntry {\n    $bm_rt = thisComp.layer('Controller')('Effects')('Color')('ADBE Color Control-0001');\n} catch (e) {\n    $bm_rt = value;\n}"},"o":{"a":0,"k":100,"ix":5},"r":1,"bm":0,"nm":"Fill 1","mn":"ADBE Vector Graphic - Fill","hd":false},{"ty":"tr","p":{"a":0,"k":[42.542,25.959],"ix":2},"a":{"a":0,"k":[0,0],"ix":1},"s":{"a":0,"k":[100,100],"ix":3},"r":{"a":0,"k":0,"ix":6},"o":{"a":0,"k":100,"ix":7},"sk":{"a":0,"k":0,"ix":4},"sa":{"a":0,"k":0,"ix":5},"nm":"Transformar"}],"nm":"Group 26","np":2,"cix":2,"bm":0,"ix":1,"mn":"ADBE Vector Group","hd":false},{"ty":"tr","p":{"a":0,"k":[301.456,218.546],"ix":2},"a":{"a":0,"k":[42.542,25.959],"ix":1},"s":{"a":0,"k":[500,500],"ix":3},"r":{"a":0,"k":0,"ix":6},"o":{"a":0,"k":100,"ix":7},"sk":{"a":0,"k":0,"ix":4},"sa":{"a":0,"k":0,"ix":5},"nm":"Transformar"}],"nm":"Layer 20 Outlines - Group 226","np":1,"cix":2,"bm":0,"ix":1,"mn":"ADBE Vector Group","hd":false},{"ty":"gr","it":[{"ty":"gr","it":[{"ind":0,"ty":"sh","ix":1,"ks":{"a":0,"k":{"i":[[4.674,0],[0,0],[0,0.352],[-0.351,0],[0,0],[0,3.971],[0,0],[-0.352,0],[0,-0.351],[0,0]],"o":[[0,0],[-0.351,0],[0,-0.351],[0,0],[3.972,0],[0,0],[0,-0.351],[0.351,0],[0,0],[0,4.674]],"v":[[13.949,7.909],[-21.791,7.909],[-22.427,7.272],[-21.791,6.636],[13.949,6.636],[21.153,-0.568],[21.153,-7.273],[21.79,-7.909],[22.427,-7.273],[22.427,-0.568]],"c":true},"ix":2},"nm":"Path 1","mn":"ADBE Vector Shape - Group","hd":false},{"ty":"fl","c":{"a":0,"k":[0.250999987125,0.063000001013,0.286000013351,1],"ix":4,"x":"var $bm_rt;\ntry {\n    $bm_rt = thisComp.layer('Controller')('Effects')('Color')('ADBE Color Control-0001');\n} catch (e) {\n    $bm_rt = value;\n}"},"o":{"a":0,"k":100,"ix":5},"r":1,"bm":0,"nm":"Fill 1","mn":"ADBE Vector Graphic - Fill","hd":false},{"ty":"tr","p":{"a":0,"k":[41.824,56.341],"ix":2},"a":{"a":0,"k":[0,0],"ix":1},"s":{"a":0,"k":[100,100],"ix":3},"r":{"a":0,"k":0,"ix":6},"o":{"a":0,"k":100,"ix":7},"sk":{"a":0,"k":0,"ix":4},"sa":{"a":0,"k":0,"ix":5},"nm":"Transformar"}],"nm":"Group 27","np":2,"cix":2,"bm":0,"ix":1,"mn":"ADBE Vector Group","hd":false},{"ty":"tr","p":{"a":0,"k":[297.867,370.456],"ix":2},"a":{"a":0,"k":[41.824,56.341],"ix":1},"s":{"a":0,"k":[500,500],"ix":3},"r":{"a":0,"k":0,"ix":6},"o":{"a":0,"k":100,"ix":7},"sk":{"a":0,"k":0,"ix":4},"sa":{"a":0,"k":0,"ix":5},"nm":"Transformar"}],"nm":"Layer 20 Outlines - Group 227","np":1,"cix":2,"bm":0,"ix":2,"mn":"ADBE Vector Group","hd":false},{"ty":"gr","it":[{"ty":"gr","it":[{"ind":0,"ty":"sh","ix":1,"ks":{"a":0,"k":{"i":[[0.352,0],[0,0],[0,4.674],[0,0],[-4.674,0],[0,0],[0,-0.352],[0.352,0],[0,0],[0,-3.971],[0,0],[-3.971,0],[0,0],[0,-0.351]],"o":[[0,0],[-4.674,0],[0,0],[0,-4.674],[0,0],[0.352,0],[0,0.351],[0,0],[-3.971,0],[0,0],[0,3.971],[0,0],[0.352,0],[0,0.352]],"v":[[6.894,29.058],[-0.491,29.058],[-8.968,20.581],[-8.968,-20.581],[-0.491,-29.058],[8.331,-29.058],[8.968,-28.421],[8.331,-27.786],[-0.491,-27.786],[-7.694,-20.581],[-7.694,20.581],[-0.491,27.786],[6.894,27.786],[7.531,28.421]],"c":true},"ix":2},"nm":"Path 1","mn":"ADBE Vector Shape - Group","hd":false},{"ty":"fl","c":{"a":0,"k":[0.250999987125,0.063000001013,0.286000013351,1],"ix":4,"x":"var $bm_rt;\ntry {\n    $bm_rt = thisComp.layer('Controller')('Effects')('Color')('ADBE Color Control-0001');\n} catch (e) {\n    $bm_rt = value;\n}"},"o":{"a":0,"k":100,"ix":5},"r":1,"bm":0,"nm":"Fill 1","mn":"ADBE Vector Graphic - Fill","hd":false},{"ty":"tr","p":{"a":0,"k":[9.219,35.192],"ix":2},"a":{"a":0,"k":[0,0],"ix":1},"s":{"a":0,"k":[100,100],"ix":3},"r":{"a":0,"k":0,"ix":6},"o":{"a":0,"k":100,"ix":7},"sk":{"a":0,"k":0,"ix":4},"sa":{"a":0,"k":0,"ix":5},"nm":"Transformar"}],"nm":"Group 28","np":2,"cix":2,"bm":0,"ix":1,"mn":"ADBE Vector Group","hd":false},{"ty":"tr","p":{"a":0,"k":[134.841,264.708],"ix":2},"a":{"a":0,"k":[9.219,35.192],"ix":1},"s":{"a":0,"k":[500,500],"ix":3},"r":{"a":0,"k":0,"ix":6},"o":{"a":0,"k":100,"ix":7},"sk":{"a":0,"k":0,"ix":4},"sa":{"a":0,"k":0,"ix":5},"nm":"Transformar"}],"nm":"Layer 20 Outlines - Group 228","np":1,"cix":2,"bm":0,"ix":3,"mn":"ADBE Vector Group","hd":false},{"ty":"gr","it":[{"ty":"gr","it":[{"ind":0,"ty":"sh","ix":1,"ks":{"a":0,"k":{"i":[[4.418,0],[0,0],[0,4.418],[0,0],[-4.419,0],[0,0],[0,-4.418],[0,0]],"o":[[0,0],[-4.419,0],[0,0],[0,-4.418],[0,0],[4.418,0],[0,0],[0,4.418]],"v":[[23.363,23.521],[-23.363,23.521],[-31.363,15.521],[-31.363,-15.521],[-23.363,-23.521],[23.363,-23.521],[31.363,-15.521],[31.363,15.521]],"c":true},"ix":2},"nm":"Path 1","mn":"ADBE Vector Shape - Group","hd":false},{"ty":"fl","c":{"a":0,"k":[0.882000029087,0.902000010014,0.917999982834,1],"ix":4,"x":"var $bm_rt;\ntry {\n    $bm_rt = thisComp.layer('Controller').effect('Color 12')('ADBE Color Control-0001');\n} catch (e) {\n    $bm_rt = value;\n}"},"o":{"a":0,"k":100,"ix":5},"r":1,"bm":0,"nm":"Fill 1","mn":"ADBE Vector Graphic - Fill","hd":false},{"ty":"tr","p":{"a":0,"k":[32.251,36.172],"ix":2},"a":{"a":0,"k":[0,0],"ix":1},"s":{"a":0,"k":[100,100],"ix":3},"r":{"a":0,"k":0,"ix":6},"o":{"a":0,"k":100,"ix":7},"sk":{"a":0,"k":0,"ix":4},"sa":{"a":0,"k":0,"ix":5},"nm":"Transformar"}],"nm":"Group 29","np":2,"cix":2,"bm":0,"ix":1,"mn":"ADBE Vector Group","hd":false},{"ty":"tr","p":{"a":0,"k":[250.001,269.61],"ix":2},"a":{"a":0,"k":[32.251,36.172],"ix":1},"s":{"a":0,"k":[500,500],"ix":3},"r":{"a":0,"k":0,"ix":6},"o":{"a":0,"k":100,"ix":7},"sk":{"a":0,"k":0,"ix":4},"sa":{"a":0,"k":0,"ix":5},"nm":"Transformar"}],"nm":"Layer 20 Outlines - Group 229","np":1,"cix":2,"bm":0,"ix":4,"mn":"ADBE Vector Group","hd":false},{"ty":"gr","it":[{"ty":"gr","it":[{"ind":0,"ty":"sh","ix":1,"ks":{"a":0,"k":{"i":[[4.418,0],[0,0],[0,4.418],[0,0],[-4.419,0],[0,0],[0,-4.418],[0,0]],"o":[[0,0],[-4.419,0],[0,0],[0,-4.418],[0,0],[4.418,0],[0,0],[0,4.418]],"v":[[23.363,26.462],[-23.363,26.462],[-31.363,18.462],[-31.363,-18.462],[-23.363,-26.462],[23.363,-26.462],[31.363,-18.462],[31.363,18.462]],"c":true},"ix":2},"nm":"Path 1","mn":"ADBE Vector Shape - Group","hd":false},{"ty":"fl","c":{"a":0,"k":[0.773000001907,0.783999979496,0.791999995708,1],"ix":4,"x":"var $bm_rt;\ntry {\n    $bm_rt = thisComp.layer('Controller').effect('Color 13')('ADBE Color Control-0001');\n} catch (e) {\n    $bm_rt = value;\n}"},"o":{"a":0,"k":100,"ix":5},"r":1,"bm":0,"nm":"Fill 1","mn":"ADBE Vector Graphic - Fill","hd":false},{"ty":"tr","p":{"a":0,"k":[32.251,33.232],"ix":2},"a":{"a":0,"k":[0,0],"ix":1},"s":{"a":0,"k":[100,100],"ix":3},"r":{"a":0,"k":0,"ix":6},"o":{"a":0,"k":100,"ix":7},"sk":{"a":0,"k":0,"ix":4},"sa":{"a":0,"k":0,"ix":5},"nm":"Transformar"}],"nm":"Group 30","np":2,"cix":2,"bm":0,"ix":1,"mn":"ADBE Vector Group","hd":false},{"ty":"tr","p":{"a":0,"k":[250.001,254.907],"ix":2},"a":{"a":0,"k":[32.251,33.232],"ix":1},"s":{"a":0,"k":[500,500],"ix":3},"r":{"a":0,"k":0,"ix":6},"o":{"a":0,"k":100,"ix":7},"sk":{"a":0,"k":0,"ix":4},"sa":{"a":0,"k":0,"ix":5},"nm":"Transformar"}],"nm":"Layer 20 Outlines - Group 330","np":1,"cix":2,"bm":0,"ix":5,"mn":"ADBE Vector Group","hd":false},{"ty":"gr","it":[{"ty":"gr","it":[{"ind":0,"ty":"sh","ix":1,"ks":{"a":0,"k":{"i":[[4.418,0],[0,0],[0,4.418],[0,0],[-4.419,0],[0,0],[0,-4.418],[0,0]],"o":[[0,0],[-4.419,0],[0,0],[0,-4.418],[0,0],[4.418,0],[0,0],[0,4.418]],"v":[[23.363,28.422],[-23.363,28.422],[-31.363,20.422],[-31.363,-20.422],[-23.363,-28.422],[23.363,-28.422],[31.363,-20.422],[31.363,20.422]],"c":true},"ix":2},"nm":"Path 1","mn":"ADBE Vector Shape - Group","hd":false},{"ty":"fl","c":{"a":0,"k":[1,1,1,1],"ix":4,"x":"var $bm_rt;\ntry {\n    $bm_rt = thisComp.layer('Controller')('Effects')('Color 5')('ADBE Color Control-0001');\n} catch (e) {\n    $bm_rt = value;\n}"},"o":{"a":0,"k":100,"ix":5},"r":1,"bm":0,"nm":"Fill 1","mn":"ADBE Vector Graphic - Fill","hd":false},{"ty":"tr","p":{"a":0,"k":[32.251,35.192],"ix":2},"a":{"a":0,"k":[0,0],"ix":1},"s":{"a":0,"k":[100,100],"ix":3},"r":{"a":0,"k":0,"ix":6},"o":{"a":0,"k":100,"ix":7},"sk":{"a":0,"k":0,"ix":4},"sa":{"a":0,"k":0,"ix":5},"nm":"Transformar"}],"nm":"Group 31","np":2,"cix":2,"bm":0,"ix":1,"mn":"ADBE Vector Group","hd":false},{"ty":"tr","p":{"a":0,"k":[250.001,264.707],"ix":2},"a":{"a":0,"k":[32.251,35.192],"ix":1},"s":{"a":0,"k":[500,500],"ix":3},"r":{"a":0,"k":0,"ix":6},"o":{"a":0,"k":100,"ix":7},"sk":{"a":0,"k":0,"ix":4},"sa":{"a":0,"k":0,"ix":5},"nm":"Transformar"}],"nm":"Layer 20 Outlines - Group 331","np":1,"cix":2,"bm":0,"ix":6,"mn":"ADBE Vector Group","hd":false}],"ip":0,"op":150.000006109625,"st":0,"ct":1,"bm":0}],"markers":[],"props":{}}